{
  "lookup": {
    "rules": {
      "[{\"prev_action\": {\"action_name\": \"action_listen\"}, \"user\": {\"intent\": \"Khoa_Phau_thuat_than_kinh_o_dau?\"}}]": "utter_Khoa_Phau_thuat_than_kinh_o_dau?",
      "[{\"prev_action\": {\"action_name\": \"action_listen\"}, \"user\": {\"intent\": \"Khoa_Phau_thuat_than_kinh_o_dau?\"}}, {\"prev_action\": {\"action_name\": \"utter_Khoa_Phau_thuat_than_kinh_o_dau?\"}, \"user\": {\"intent\": \"Khoa_Phau_thuat_than_kinh_o_dau?\"}}]": "action_listen",
      "[{\"prev_action\": {\"action_name\": \"action_listen\"}, \"user\": {\"intent\": \"Nha_tang_le_benh_vien_E_o_dau?\"}}]": "utter_Nha_tang_le_benh_vien_E_o_dau?",
      "[{\"prev_action\": {\"action_name\": \"action_listen\"}, \"user\": {\"intent\": \"Nha_tang_le_benh_vien_E_o_dau?\"}}, {\"prev_action\": {\"action_name\": \"utter_Nha_tang_le_benh_vien_E_o_dau?\"}, \"user\": {\"intent\": \"Nha_tang_le_benh_vien_E_o_dau?\"}}]": "action_listen",
      "[{\"prev_action\": {\"action_name\": \"action_listen\"}, \"user\": {\"intent\": \"Khoa_vi_sinh_o_dau?\"}}]": "utter_Khoa_vi_sinh_o_dau?",
      "[{\"prev_action\": {\"action_name\": \"action_listen\"}, \"user\": {\"intent\": \"Khoa_vi_sinh_o_dau?\"}}, {\"prev_action\": {\"action_name\": \"utter_Khoa_vi_sinh_o_dau?\"}, \"user\": {\"intent\": \"Khoa_vi_sinh_o_dau?\"}}]": "action_listen",
      "[{\"prev_action\": {\"action_name\": \"action_listen\"}, \"user\": {\"intent\": \"Khoa_Tai_mui_hong_o_dau\"}}]": "utter_Khoa_Tai_mui_hong_o_dau",
      "[{\"prev_action\": {\"action_name\": \"action_listen\"}, \"user\": {\"intent\": \"Khoa_Tai_mui_hong_o_dau\"}}, {\"prev_action\": {\"action_name\": \"utter_Khoa_Tai_mui_hong_o_dau\"}, \"user\": {\"intent\": \"Khoa_Tai_mui_hong_o_dau\"}}]": "action_listen",
      "[{\"prev_action\": {\"action_name\": \"action_listen\"}, \"user\": {\"intent\": \"Khoa_tieu_hoa_o_dau?\"}}]": "utter_Khoa_tieu_hoa_o_dau?",
      "[{\"prev_action\": {\"action_name\": \"action_listen\"}, \"user\": {\"intent\": \"Khoa_tieu_hoa_o_dau?\"}}, {\"prev_action\": {\"action_name\": \"utter_Khoa_tieu_hoa_o_dau?\"}, \"user\": {\"intent\": \"Khoa_tieu_hoa_o_dau?\"}}]": "action_listen",
      "[{\"prev_action\": {\"action_name\": \"action_listen\"}, \"user\": {\"intent\": \"toi_bi_tieu_nhieu_vao_ban_dem\"}}]": "utter_toi_bi_tieu_nhieu_vao_ban_dem",
      "[{\"prev_action\": {\"action_name\": \"action_listen\"}, \"user\": {\"intent\": \"toi_bi_tieu_nhieu_vao_ban_dem\"}}, {\"prev_action\": {\"action_name\": \"utter_toi_bi_tieu_nhieu_vao_ban_dem\"}, \"user\": {\"intent\": \"toi_bi_tieu_nhieu_vao_ban_dem\"}}]": "action_listen",
      "[{\"prev_action\": {\"action_name\": \"action_listen\"}, \"user\": {\"intent\": \"Khoa_huyet_hoc_o_dau?\"}}]": "utter_Khoa_huyet_hoc_o_dau?",
      "[{\"prev_action\": {\"action_name\": \"action_listen\"}, \"user\": {\"intent\": \"Khoa_huyet_hoc_o_dau?\"}}, {\"prev_action\": {\"action_name\": \"utter_Khoa_huyet_hoc_o_dau?\"}, \"user\": {\"intent\": \"Khoa_huyet_hoc_o_dau?\"}}]": "action_listen",
      "[{\"prev_action\": {\"action_name\": \"action_listen\"}, \"user\": {\"intent\": \"Thu_ngan_o_dau?\"}}]": "utter_Thu_ngan_o_dau?",
      "[{\"prev_action\": {\"action_name\": \"action_listen\"}, \"user\": {\"intent\": \"Thu_ngan_o_dau?\"}}, {\"prev_action\": {\"action_name\": \"utter_Thu_ngan_o_dau?\"}, \"user\": {\"intent\": \"Thu_ngan_o_dau?\"}}]": "action_listen",
      "[{\"prev_action\": {\"action_name\": \"action_listen\"}, \"user\": {\"intent\": \"Em_muon_dang_ki_kham_theo_yeu_cau\"}}]": "utter_Em_muon_dang_ki_kham_theo_yeu_cau",
      "[{\"prev_action\": {\"action_name\": \"action_listen\"}, \"user\": {\"intent\": \"Em_muon_dang_ki_kham_theo_yeu_cau\"}}, {\"prev_action\": {\"action_name\": \"utter_Em_muon_dang_ki_kham_theo_yeu_cau\"}, \"user\": {\"intent\": \"Em_muon_dang_ki_kham_theo_yeu_cau\"}}]": "action_listen",
      "[{\"prev_action\": {\"action_name\": \"action_listen\"}, \"user\": {\"intent\": \"Photo_giay_to_o_dau?\"}}]": "utter_Photo_giay_to_o_dau?",
      "[{\"prev_action\": {\"action_name\": \"action_listen\"}, \"user\": {\"intent\": \"Photo_giay_to_o_dau?\"}}, {\"prev_action\": {\"action_name\": \"utter_Photo_giay_to_o_dau?\"}, \"user\": {\"intent\": \"Photo_giay_to_o_dau?\"}}]": "action_listen",
      "[{\"prev_action\": {\"action_name\": \"action_listen\"}, \"user\": {\"intent\": \"Nha_luu_tru_benh_vien_o_dau?\"}}]": "utter_Nha_luu_tru_benh_vien_o_dau?",
      "[{\"prev_action\": {\"action_name\": \"action_listen\"}, \"user\": {\"intent\": \"Nha_luu_tru_benh_vien_o_dau?\"}}, {\"prev_action\": {\"action_name\": \"utter_Nha_luu_tru_benh_vien_o_dau?\"}, \"user\": {\"intent\": \"Nha_luu_tru_benh_vien_o_dau?\"}}]": "action_listen",
      "[{\"prev_action\": {\"action_name\": \"action_listen\"}, \"user\": {\"intent\": \"Khoa_y_hoc_co_truyen_o_dau?\"}}]": "utter_Khoa_y_hoc_co_truyen_o_dau?",
      "[{\"prev_action\": {\"action_name\": \"action_listen\"}, \"user\": {\"intent\": \"Khoa_y_hoc_co_truyen_o_dau?\"}}, {\"prev_action\": {\"action_name\": \"utter_Khoa_y_hoc_co_truyen_o_dau?\"}, \"user\": {\"intent\": \"Khoa_y_hoc_co_truyen_o_dau?\"}}]": "action_listen",
      "[{\"prev_action\": {\"action_name\": \"action_listen\"}, \"user\": {\"intent\": \"toi_bi_dau_tai\"}}]": "utter_toi_bi_dau_tai",
      "[{\"prev_action\": {\"action_name\": \"action_listen\"}, \"user\": {\"intent\": \"toi_bi_dau_tai\"}}, {\"prev_action\": {\"action_name\": \"utter_toi_bi_dau_tai\"}, \"user\": {\"intent\": \"toi_bi_dau_tai\"}}]": "action_listen",
      "[{\"prev_action\": {\"action_name\": \"action_listen\"}, \"user\": {\"intent\": \"Em_muon_dang_ki_kham_bao_hiem_y_te\"}}]": "utter_Em_muon_dang_ki_kham_bao_hiem_y_te",
      "[{\"prev_action\": {\"action_name\": \"action_listen\"}, \"user\": {\"intent\": \"Em_muon_dang_ki_kham_bao_hiem_y_te\"}}, {\"prev_action\": {\"action_name\": \"utter_Em_muon_dang_ki_kham_bao_hiem_y_te\"}, \"user\": {\"intent\": \"Em_muon_dang_ki_kham_bao_hiem_y_te\"}}]": "action_listen",
      "[{\"prev_action\": {\"action_name\": \"action_listen\"}, \"user\": {\"intent\": \"hoi_tuoi_robot\"}}]": "utter_hoi_tuoi_robot",
      "[{\"prev_action\": {\"action_name\": \"action_listen\"}, \"user\": {\"intent\": \"hoi_tuoi_robot\"}}, {\"prev_action\": {\"action_name\": \"utter_hoi_tuoi_robot\"}, \"user\": {\"intent\": \"hoi_tuoi_robot\"}}]": "action_listen",
      "[{\"prev_action\": {\"action_name\": \"action_listen\"}, \"user\": {\"intent\": \"Khoa_noi_gan_mat_o_dau?\"}}]": "utter_Khoa_noi_gan_mat_o_dau?",
      "[{\"prev_action\": {\"action_name\": \"action_listen\"}, \"user\": {\"intent\": \"Khoa_noi_gan_mat_o_dau?\"}}, {\"prev_action\": {\"action_name\": \"utter_Khoa_noi_gan_mat_o_dau?\"}, \"user\": {\"intent\": \"Khoa_noi_gan_mat_o_dau?\"}}]": "action_listen",
      "[{\"prev_action\": {\"action_name\": \"action_listen\"}, \"user\": {\"intent\": \"Khoa_ngoai_tong_hop_o_dau?\"}}]": "utter_Khoa_ngoai_tong_hop_o_dau?",
      "[{\"prev_action\": {\"action_name\": \"action_listen\"}, \"user\": {\"intent\": \"Khoa_ngoai_tong_hop_o_dau?\"}}, {\"prev_action\": {\"action_name\": \"utter_Khoa_ngoai_tong_hop_o_dau?\"}, \"user\": {\"intent\": \"Khoa_ngoai_tong_hop_o_dau?\"}}]": "action_listen",
      "[{\"prev_action\": {\"action_name\": \"action_listen\"}, \"user\": {\"intent\": \"toi_bi_dau_mat\"}}]": "utter_toi_bi_dau_mat",
      "[{\"prev_action\": {\"action_name\": \"action_listen\"}, \"user\": {\"intent\": \"toi_bi_dau_mat\"}}, {\"prev_action\": {\"action_name\": \"utter_toi_bi_dau_mat\"}, \"user\": {\"intent\": \"toi_bi_dau_mat\"}}]": "action_listen",
      "[{\"prev_action\": {\"action_name\": \"action_listen\"}, \"user\": {\"intent\": \"Nha_thuoc_benh_vien_o_dau?\"}}]": "utter_Nha_thuoc_benh_vien_o_dau?",
      "[{\"prev_action\": {\"action_name\": \"action_listen\"}, \"user\": {\"intent\": \"Nha_thuoc_benh_vien_o_dau?\"}}, {\"prev_action\": {\"action_name\": \"utter_Nha_thuoc_benh_vien_o_dau?\"}, \"user\": {\"intent\": \"Nha_thuoc_benh_vien_o_dau?\"}}]": "action_listen",
      "[{\"prev_action\": {\"action_name\": \"action_listen\"}, \"user\": {\"intent\": \"Khoa_noi_tong_hop_o_dau?\"}}]": "utter_Khoa_noi_tong_hop_o_dau?",
      "[{\"prev_action\": {\"action_name\": \"action_listen\"}, \"user\": {\"intent\": \"Khoa_noi_tong_hop_o_dau?\"}}, {\"prev_action\": {\"action_name\": \"utter_Khoa_noi_tong_hop_o_dau?\"}, \"user\": {\"intent\": \"Khoa_noi_tong_hop_o_dau?\"}}]": "action_listen",
      "[{\"prev_action\": {\"action_name\": \"action_listen\"}, \"user\": {\"intent\": \"khen_chatbot\"}}]": "utter_khen_chatbot",
      "[{\"prev_action\": {\"action_name\": \"action_listen\"}, \"user\": {\"intent\": \"khen_chatbot\"}}, {\"prev_action\": {\"action_name\": \"utter_khen_chatbot\"}, \"user\": {\"intent\": \"khen_chatbot\"}}]": "action_listen",
      "[{\"prev_action\": {\"action_name\": \"action_listen\"}, \"user\": {\"intent\": \"Nha_ve_sinh__o_dau?\"}}]": "utter_Nha_ve_sinh__o_dau?",
      "[{\"prev_action\": {\"action_name\": \"action_listen\"}, \"user\": {\"intent\": \"Nha_ve_sinh__o_dau?\"}}, {\"prev_action\": {\"action_name\": \"utter_Nha_ve_sinh__o_dau?\"}, \"user\": {\"intent\": \"Nha_ve_sinh__o_dau?\"}}]": "action_listen",
      "[{\"prev_action\": {\"action_name\": \"action_listen\"}, \"user\": {\"intent\": \"Nha_P\"}}]": "utter_Nha_P",
      "[{\"prev_action\": {\"action_name\": \"action_listen\"}, \"user\": {\"intent\": \"Nha_P\"}}, {\"prev_action\": {\"action_name\": \"utter_Nha_P\"}, \"user\": {\"intent\": \"Nha_P\"}}]": "action_listen",
      "[{\"prev_action\": {\"action_name\": \"action_listen\"}, \"user\": {\"intent\": \"toi_bi_dau_xuong_khop\"}}]": "utter_toi_bi_dau_xuong_khop",
      "[{\"prev_action\": {\"action_name\": \"action_listen\"}, \"user\": {\"intent\": \"toi_bi_dau_xuong_khop\"}}, {\"prev_action\": {\"action_name\": \"utter_toi_bi_dau_xuong_khop\"}, \"user\": {\"intent\": \"toi_bi_dau_xuong_khop\"}}]": "action_listen",
      "[{\"prev_action\": {\"action_name\": \"action_listen\"}, \"user\": {\"intent\": \"Khoa_ho_hap_o_dau?\"}}]": "utter_Khoa_ho_hap_o_dau?",
      "[{\"prev_action\": {\"action_name\": \"action_listen\"}, \"user\": {\"intent\": \"Khoa_ho_hap_o_dau?\"}}, {\"prev_action\": {\"action_name\": \"utter_Khoa_ho_hap_o_dau?\"}, \"user\": {\"intent\": \"Khoa_ho_hap_o_dau?\"}}]": "action_listen",
      "[{\"prev_action\": {\"action_name\": \"action_listen\"}, \"user\": {\"intent\": \"toi_bi_\\u0111au_tuc_nguc\"}}]": "utter_toi_bi_dau_tuc_nguc",
      "[{\"prev_action\": {\"action_name\": \"action_listen\"}, \"user\": {\"intent\": \"toi_bi_\\u0111au_tuc_nguc\"}}, {\"prev_action\": {\"action_name\": \"utter_toi_bi_dau_tuc_nguc\"}, \"user\": {\"intent\": \"toi_bi_\\u0111au_tuc_nguc\"}}]": "action_listen",
      "[{\"prev_action\": {\"action_name\": \"action_listen\"}, \"user\": {\"intent\": \"Khoa_phau_thuat_-_gay_me_hoi_suc_o_dau?\"}}]": "utter_Khoa_phau_thuat_-_gay_me_hoi_suc_o_dau?",
      "[{\"prev_action\": {\"action_name\": \"action_listen\"}, \"user\": {\"intent\": \"Khoa_phau_thuat_-_gay_me_hoi_suc_o_dau?\"}}, {\"prev_action\": {\"action_name\": \"utter_Khoa_phau_thuat_-_gay_me_hoi_suc_o_dau?\"}, \"user\": {\"intent\": \"Khoa_phau_thuat_-_gay_me_hoi_suc_o_dau?\"}}]": "action_listen",
      "[{\"prev_action\": {\"action_name\": \"action_listen\"}, \"user\": {\"intent\": \"toi_di_kham_thai\"}}]": "utter_toi_di_kham_thai",
      "[{\"prev_action\": {\"action_name\": \"action_listen\"}, \"user\": {\"intent\": \"toi_di_kham_thai\"}}, {\"prev_action\": {\"action_name\": \"utter_toi_di_kham_thai\"}, \"user\": {\"intent\": \"toi_di_kham_thai\"}}]": "action_listen",
      "[{\"prev_action\": {\"action_name\": \"action_listen\"}, \"user\": {\"intent\": \"Xin_dau_vao_don_thuoc_o_dau\"}}]": "utter_Xin_dau_vao_don_thuoc_o_dau",
      "[{\"prev_action\": {\"action_name\": \"action_listen\"}, \"user\": {\"intent\": \"Xin_dau_vao_don_thuoc_o_dau\"}}, {\"prev_action\": {\"action_name\": \"utter_Xin_dau_vao_don_thuoc_o_dau\"}, \"user\": {\"intent\": \"Xin_dau_vao_don_thuoc_o_dau\"}}]": "action_listen",
      "[{\"prev_action\": {\"action_name\": \"action_listen\"}, \"user\": {\"intent\": \"Khoa_Kiem_tra_suc_khoe_o_dau?\"}}]": "utter_Khoa_Kiem_tra_suc_khoe_o_dau?",
      "[{\"prev_action\": {\"action_name\": \"action_listen\"}, \"user\": {\"intent\": \"Khoa_Kiem_tra_suc_khoe_o_dau?\"}}, {\"prev_action\": {\"action_name\": \"utter_Khoa_Kiem_tra_suc_khoe_o_dau?\"}, \"user\": {\"intent\": \"Khoa_Kiem_tra_suc_khoe_o_dau?\"}}]": "action_listen",
      "[{\"prev_action\": {\"action_name\": \"action_listen\"}, \"user\": {\"intent\": \"Kham_co_xuong_khop_tien_si_o_dau?\"}}]": "utter_Kham_co_xuong_khop_tien_si_o_dau?",
      "[{\"prev_action\": {\"action_name\": \"action_listen\"}, \"user\": {\"intent\": \"Kham_co_xuong_khop_tien_si_o_dau?\"}}, {\"prev_action\": {\"action_name\": \"utter_Kham_co_xuong_khop_tien_si_o_dau?\"}, \"user\": {\"intent\": \"Kham_co_xuong_khop_tien_si_o_dau?\"}}]": "action_listen",
      "[{\"prev_action\": {\"action_name\": \"action_listen\"}, \"user\": {\"intent\": \"Phong_ke_hoach_tong_hop_o_dau?\"}}]": "utter_Phong_ke_hoach_tong_hop_o_dau?",
      "[{\"prev_action\": {\"action_name\": \"action_listen\"}, \"user\": {\"intent\": \"Phong_ke_hoach_tong_hop_o_dau?\"}}, {\"prev_action\": {\"action_name\": \"utter_Phong_ke_hoach_tong_hop_o_dau?\"}, \"user\": {\"intent\": \"Phong_ke_hoach_tong_hop_o_dau?\"}}]": "action_listen",
      "[{\"prev_action\": {\"action_name\": \"action_listen\"}, \"user\": {\"intent\": \"Khoa_noi_than_kinh_o_dau?\"}}]": "utter_Khoa_noi_than_kinh_o_dau?",
      "[{\"prev_action\": {\"action_name\": \"action_listen\"}, \"user\": {\"intent\": \"Khoa_noi_than_kinh_o_dau?\"}}, {\"prev_action\": {\"action_name\": \"utter_Khoa_noi_than_kinh_o_dau?\"}, \"user\": {\"intent\": \"Khoa_noi_than_kinh_o_dau?\"}}]": "action_listen",
      "[{\"prev_action\": {\"action_name\": \"action_listen\"}, \"user\": {\"intent\": \"Khoa_Rang_ham_mat_o_dau\"}}]": "utter_Khoa_Rang_ham_mat_o_dau",
      "[{\"prev_action\": {\"action_name\": \"action_listen\"}, \"user\": {\"intent\": \"Khoa_Rang_ham_mat_o_dau\"}}, {\"prev_action\": {\"action_name\": \"utter_Khoa_Rang_ham_mat_o_dau\"}, \"user\": {\"intent\": \"Khoa_Rang_ham_mat_o_dau\"}}]": "action_listen",
      "[{\"prev_action\": {\"action_name\": \"action_listen\"}, \"user\": {\"intent\": \"Khoa_San_o_dau?\"}}]": "utter_Khoa_San_o_dau?",
      "[{\"prev_action\": {\"action_name\": \"action_listen\"}, \"user\": {\"intent\": \"Khoa_San_o_dau?\"}}, {\"prev_action\": {\"action_name\": \"utter_Khoa_San_o_dau?\"}, \"user\": {\"intent\": \"Khoa_San_o_dau?\"}}]": "action_listen",
      "[{\"prev_action\": {\"action_name\": \"action_listen\"}, \"user\": {\"intent\": \"Khoa_ngoai_chan_thuong_o_dau?\"}}]": "utter_Khoa_ngoai_chan_thuong_o_dau?",
      "[{\"prev_action\": {\"action_name\": \"action_listen\"}, \"user\": {\"intent\": \"Khoa_ngoai_chan_thuong_o_dau?\"}}, {\"prev_action\": {\"action_name\": \"utter_Khoa_ngoai_chan_thuong_o_dau?\"}, \"user\": {\"intent\": \"Khoa_ngoai_chan_thuong_o_dau?\"}}]": "action_listen",
      "[{\"prev_action\": {\"action_name\": \"action_listen\"}, \"user\": {\"intent\": \"Nha_B\"}}]": "utter_Nha_B",
      "[{\"prev_action\": {\"action_name\": \"action_listen\"}, \"user\": {\"intent\": \"Nha_B\"}}, {\"prev_action\": {\"action_name\": \"utter_Nha_B\"}, \"user\": {\"intent\": \"Nha_B\"}}]": "action_listen",
      "[{\"prev_action\": {\"action_name\": \"action_listen\"}, \"user\": {\"intent\": \"Thanh_toan_BHYT_o_dau?\"}}]": "utter_Thanh_toan_BHYT_o_dau?",
      "[{\"prev_action\": {\"action_name\": \"action_listen\"}, \"user\": {\"intent\": \"Thanh_toan_BHYT_o_dau?\"}}, {\"prev_action\": {\"action_name\": \"utter_Thanh_toan_BHYT_o_dau?\"}, \"user\": {\"intent\": \"Thanh_toan_BHYT_o_dau?\"}}]": "action_listen",
      "[{\"prev_action\": {\"action_name\": \"action_listen\"}, \"user\": {\"intent\": \"Lay_mau_o_dau?\"}}]": "utter_Lay_mau_o_dau?",
      "[{\"prev_action\": {\"action_name\": \"action_listen\"}, \"user\": {\"intent\": \"Lay_mau_o_dau?\"}}, {\"prev_action\": {\"action_name\": \"utter_Lay_mau_o_dau?\"}, \"user\": {\"intent\": \"Lay_mau_o_dau?\"}}]": "action_listen",
      "[{\"prev_action\": {\"action_name\": \"action_listen\"}, \"user\": {\"intent\": \"Khoa_chan_doan_hinh_anh_o_dau?\"}}]": "utter_Khoa_chan_doan_hinh_anh_o_dau?",
      "[{\"prev_action\": {\"action_name\": \"action_listen\"}, \"user\": {\"intent\": \"Khoa_chan_doan_hinh_anh_o_dau?\"}}, {\"prev_action\": {\"action_name\": \"utter_Khoa_chan_doan_hinh_anh_o_dau?\"}, \"user\": {\"intent\": \"Khoa_chan_doan_hinh_anh_o_dau?\"}}]": "action_listen",
      "[{\"prev_action\": {\"action_name\": \"action_listen\"}, \"user\": {\"intent\": \"Sao_luu_trich_luc_benh_an_o_dau?\"}}]": "utter_Sao_luu_trich_luc_benh_an_o_dau?",
      "[{\"prev_action\": {\"action_name\": \"action_listen\"}, \"user\": {\"intent\": \"Sao_luu_trich_luc_benh_an_o_dau?\"}}, {\"prev_action\": {\"action_name\": \"utter_Sao_luu_trich_luc_benh_an_o_dau?\"}, \"user\": {\"intent\": \"Sao_luu_trich_luc_benh_an_o_dau?\"}}]": "action_listen",
      "[{\"prev_action\": {\"action_name\": \"action_listen\"}, \"user\": {\"intent\": \"Thoi_gian_lam_viec_cua_benh_vien\"}}]": "utter_Thoi_gian_lam_viec_cua_benh_vien",
      "[{\"prev_action\": {\"action_name\": \"action_listen\"}, \"user\": {\"intent\": \"Thoi_gian_lam_viec_cua_benh_vien\"}}, {\"prev_action\": {\"action_name\": \"utter_Thoi_gian_lam_viec_cua_benh_vien\"}, \"user\": {\"intent\": \"Thoi_gian_lam_viec_cua_benh_vien\"}}]": "action_listen",
      "[{\"prev_action\": {\"action_name\": \"action_listen\"}, \"user\": {\"intent\": \"toi_bi_nga_xe\"}}]": "utter_toi_bi_nga_xe",
      "[{\"prev_action\": {\"action_name\": \"action_listen\"}, \"user\": {\"intent\": \"toi_bi_nga_xe\"}}, {\"prev_action\": {\"action_name\": \"utter_toi_bi_nga_xe\"}, \"user\": {\"intent\": \"toi_bi_nga_xe\"}}]": "action_listen",
      "[{\"prev_action\": {\"action_name\": \"action_listen\"}, \"user\": {\"intent\": \"Nha_D\"}}]": "utter_Nha_D",
      "[{\"prev_action\": {\"action_name\": \"action_listen\"}, \"user\": {\"intent\": \"Nha_D\"}}, {\"prev_action\": {\"action_name\": \"utter_Nha_D\"}, \"user\": {\"intent\": \"Nha_D\"}}]": "action_listen",
      "[{\"prev_action\": {\"action_name\": \"action_listen\"}, \"user\": {\"intent\": \"toi_bi_di_ngoai\"}}]": "utter_toi_bi_di_ngoai",
      "[{\"prev_action\": {\"action_name\": \"action_listen\"}, \"user\": {\"intent\": \"toi_bi_di_ngoai\"}}, {\"prev_action\": {\"action_name\": \"utter_toi_bi_di_ngoai\"}, \"user\": {\"intent\": \"toi_bi_di_ngoai\"}}]": "action_listen",
      "[{\"prev_action\": {\"action_name\": \"action_listen\"}, \"user\": {\"intent\": \"Giay_to_can_thiet_kham_la_gi?\"}}]": "utter_Giay_to_can_thiet_kham_la_gi?",
      "[{\"prev_action\": {\"action_name\": \"action_listen\"}, \"user\": {\"intent\": \"Giay_to_can_thiet_kham_la_gi?\"}}, {\"prev_action\": {\"action_name\": \"utter_Giay_to_can_thiet_kham_la_gi?\"}, \"user\": {\"intent\": \"Giay_to_can_thiet_kham_la_gi?\"}}]": "action_listen",
      "[{\"prev_action\": {\"action_name\": \"action_listen\"}, \"user\": {\"intent\": \"Khoa_Phau_thuat_tao_hinh_tham_my_o_dau?\"}}]": "utter_Khoa_Phau_thuat_tao_hinh_tham_my_o_dau?",
      "[{\"prev_action\": {\"action_name\": \"action_listen\"}, \"user\": {\"intent\": \"Khoa_Phau_thuat_tao_hinh_tham_my_o_dau?\"}}, {\"prev_action\": {\"action_name\": \"utter_Khoa_Phau_thuat_tao_hinh_tham_my_o_dau?\"}, \"user\": {\"intent\": \"Khoa_Phau_thuat_tao_hinh_tham_my_o_dau?\"}}]": "action_listen",
      "[{\"prev_action\": {\"action_name\": \"action_listen\"}, \"user\": {\"intent\": \"Tra_so_BHYT_o_dau?\"}}]": "utter_Tra_so_BHYT_o_dau?",
      "[{\"prev_action\": {\"action_name\": \"action_listen\"}, \"user\": {\"intent\": \"Tra_so_BHYT_o_dau?\"}}, {\"prev_action\": {\"action_name\": \"utter_Tra_so_BHYT_o_dau?\"}, \"user\": {\"intent\": \"Tra_so_BHYT_o_dau?\"}}]": "action_listen",
      "[{\"prev_action\": {\"action_name\": \"action_listen\"}, \"user\": {\"intent\": \"chao_hoi\"}}]": "utter_chao_hoi",
      "[{\"prev_action\": {\"action_name\": \"action_listen\"}, \"user\": {\"intent\": \"chao_hoi\"}}, {\"prev_action\": {\"action_name\": \"utter_chao_hoi\"}, \"user\": {\"intent\": \"chao_hoi\"}}]": "action_listen",
      "[{\"prev_action\": {\"action_name\": \"action_listen\"}, \"user\": {\"intent\": \"Khoa_than_tiet_nieu_va_loc_mau_o_dau?\"}}]": "utter_Khoa_than_tiet_nieu_va_loc_mau_o_dau?",
      "[{\"prev_action\": {\"action_name\": \"action_listen\"}, \"user\": {\"intent\": \"Khoa_than_tiet_nieu_va_loc_mau_o_dau?\"}}, {\"prev_action\": {\"action_name\": \"utter_Khoa_than_tiet_nieu_va_loc_mau_o_dau?\"}, \"user\": {\"intent\": \"Khoa_than_tiet_nieu_va_loc_mau_o_dau?\"}}]": "action_listen",
      "[{\"prev_action\": {\"action_name\": \"action_listen\"}, \"user\": {\"intent\": \"hoi_an_chua\"}}]": "utter_hoi_an_chua",
      "[{\"prev_action\": {\"action_name\": \"action_listen\"}, \"user\": {\"intent\": \"hoi_an_chua\"}}, {\"prev_action\": {\"action_name\": \"utter_hoi_an_chua\"}, \"user\": {\"intent\": \"hoi_an_chua\"}}]": "action_listen",
      "[{\"prev_action\": {\"action_name\": \"action_listen\"}, \"user\": {\"intent\": \"cam_on\"}}]": "utter_cam_on",
      "[{\"prev_action\": {\"action_name\": \"action_listen\"}, \"user\": {\"intent\": \"cam_on\"}}, {\"prev_action\": {\"action_name\": \"utter_cam_on\"}, \"user\": {\"intent\": \"cam_on\"}}]": "action_listen",
      "[{\"prev_action\": {\"action_name\": \"action_listen\"}, \"user\": {\"intent\": \"Khoa_than_nhan_tao_o_dau?\"}}]": "utter_Khoa_than_nhan_tao_o_dau?",
      "[{\"prev_action\": {\"action_name\": \"action_listen\"}, \"user\": {\"intent\": \"Khoa_than_nhan_tao_o_dau?\"}}, {\"prev_action\": {\"action_name\": \"utter_Khoa_than_nhan_tao_o_dau?\"}, \"user\": {\"intent\": \"Khoa_than_nhan_tao_o_dau?\"}}]": "action_listen",
      "[{\"prev_action\": {\"action_name\": \"action_listen\"}, \"user\": {\"intent\": \"Khoa_kham_benh_o_dau\"}}]": "utter_Khoa_kham_benh_o_dau",
      "[{\"prev_action\": {\"action_name\": \"action_listen\"}, \"user\": {\"intent\": \"Khoa_kham_benh_o_dau\"}}, {\"prev_action\": {\"action_name\": \"utter_Khoa_kham_benh_o_dau\"}, \"user\": {\"intent\": \"Khoa_kham_benh_o_dau\"}}]": "action_listen",
      "[{\"prev_action\": {\"action_name\": \"action_listen\"}, \"user\": {\"intent\": \"hoi_ten_robot\"}}]": "utter_hoi_ten_robot",
      "[{\"prev_action\": {\"action_name\": \"action_listen\"}, \"user\": {\"intent\": \"hoi_ten_robot\"}}, {\"prev_action\": {\"action_name\": \"utter_hoi_ten_robot\"}, \"user\": {\"intent\": \"hoi_ten_robot\"}}]": "action_listen",
      "[{\"prev_action\": {\"action_name\": \"action_listen\"}, \"user\": {\"intent\": \"Nha_C\"}}]": "utter_Nha_C",
      "[{\"prev_action\": {\"action_name\": \"action_listen\"}, \"user\": {\"intent\": \"Nha_C\"}}, {\"prev_action\": {\"action_name\": \"utter_Nha_C\"}, \"user\": {\"intent\": \"Nha_C\"}}]": "action_listen",
      "[{\"prev_action\": {\"action_name\": \"action_listen\"}, \"user\": {\"intent\": \"Khoa_Noi_nhi_tong_hop_o_dau?\"}}]": "utter_Khoa_Noi_nhi_tong_hop_o_dau?",
      "[{\"prev_action\": {\"action_name\": \"action_listen\"}, \"user\": {\"intent\": \"Khoa_Noi_nhi_tong_hop_o_dau?\"}}, {\"prev_action\": {\"action_name\": \"utter_Khoa_Noi_nhi_tong_hop_o_dau?\"}, \"user\": {\"intent\": \"Khoa_Noi_nhi_tong_hop_o_dau?\"}}]": "action_listen",
      "[{\"prev_action\": {\"action_name\": \"action_listen\"}, \"user\": {\"intent\": \"Phong_kham_ngoai_tong_hop_o_dau?\"}}]": "utter_Phong_kham_ngoai_tong_hop_o_dau?",
      "[{\"prev_action\": {\"action_name\": \"action_listen\"}, \"user\": {\"intent\": \"Phong_kham_ngoai_tong_hop_o_dau?\"}}, {\"prev_action\": {\"action_name\": \"utter_Phong_kham_ngoai_tong_hop_o_dau?\"}, \"user\": {\"intent\": \"Phong_kham_ngoai_tong_hop_o_dau?\"}}]": "action_listen",
      "[{\"prev_action\": {\"action_name\": \"action_listen\"}, \"user\": {\"intent\": \"Khoa_tham_do_chuc_nang_-_noi_soi_o_dau?\"}}]": "utter_Khoa_tham_do_chuc_nang_-_noi_soi_o_dau?",
      "[{\"prev_action\": {\"action_name\": \"action_listen\"}, \"user\": {\"intent\": \"Khoa_tham_do_chuc_nang_-_noi_soi_o_dau?\"}}, {\"prev_action\": {\"action_name\": \"utter_Khoa_tham_do_chuc_nang_-_noi_soi_o_dau?\"}, \"user\": {\"intent\": \"Khoa_tham_do_chuc_nang_-_noi_soi_o_dau?\"}}]": "action_listen",
      "[{\"prev_action\": {\"action_name\": \"action_listen\"}, \"user\": {\"intent\": \"Khoa_tim_mach_o_dau?\"}}]": "utter_Khoa_tim_mach_o_dau?",
      "[{\"prev_action\": {\"action_name\": \"action_listen\"}, \"user\": {\"intent\": \"Khoa_tim_mach_o_dau?\"}}, {\"prev_action\": {\"action_name\": \"utter_Khoa_tim_mach_o_dau?\"}, \"user\": {\"intent\": \"Khoa_tim_mach_o_dau?\"}}]": "action_listen",
      "[{\"prev_action\": {\"action_name\": \"action_listen\"}, \"user\": {\"intent\": \"Khoa_ung_buou_o_dau?\"}}]": "utter_Khoa_ung_buou_o_dau?",
      "[{\"prev_action\": {\"action_name\": \"action_listen\"}, \"user\": {\"intent\": \"Khoa_ung_buou_o_dau?\"}}, {\"prev_action\": {\"action_name\": \"utter_Khoa_ung_buou_o_dau?\"}, \"user\": {\"intent\": \"Khoa_ung_buou_o_dau?\"}}]": "action_listen",
      "[{\"prev_action\": {\"action_name\": \"action_listen\"}, \"user\": {\"intent\": \"toi_bi_dau_bung\"}}]": "utter_toi_bi_dau_bung",
      "[{\"prev_action\": {\"action_name\": \"action_listen\"}, \"user\": {\"intent\": \"toi_bi_dau_bung\"}}, {\"prev_action\": {\"action_name\": \"utter_toi_bi_dau_bung\"}, \"user\": {\"intent\": \"toi_bi_dau_bung\"}}]": "action_listen",
      "[{\"prev_action\": {\"action_name\": \"action_listen\"}, \"user\": {\"intent\": \"Khoa_dinh_duong_o_dau?\"}}]": "utter_Khoa_dinh_duong_o_dau?",
      "[{\"prev_action\": {\"action_name\": \"action_listen\"}, \"user\": {\"intent\": \"Khoa_dinh_duong_o_dau?\"}}, {\"prev_action\": {\"action_name\": \"utter_Khoa_dinh_duong_o_dau?\"}, \"user\": {\"intent\": \"Khoa_dinh_duong_o_dau?\"}}]": "action_listen",
      "[{\"prev_action\": {\"action_name\": \"action_listen\"}, \"user\": {\"intent\": \"toi_bi_dau_hong\"}}]": "utter_toi_bi_dau_hong",
      "[{\"prev_action\": {\"action_name\": \"action_listen\"}, \"user\": {\"intent\": \"toi_bi_dau_hong\"}}, {\"prev_action\": {\"action_name\": \"utter_toi_bi_dau_hong\"}, \"user\": {\"intent\": \"toi_bi_dau_hong\"}}]": "action_listen",
      "[{\"prev_action\": {\"action_name\": \"action_listen\"}, \"user\": {\"intent\": \"Khoa_benh_nhiet_doi_o_dau?\"}}]": "utter_Khoa_benh_nhiet_doi_o_dau?",
      "[{\"prev_action\": {\"action_name\": \"action_listen\"}, \"user\": {\"intent\": \"Khoa_benh_nhiet_doi_o_dau?\"}}, {\"prev_action\": {\"action_name\": \"utter_Khoa_benh_nhiet_doi_o_dau?\"}, \"user\": {\"intent\": \"Khoa_benh_nhiet_doi_o_dau?\"}}]": "action_listen",
      "[{\"prev_action\": {\"action_name\": \"action_listen\"}, \"user\": {\"intent\": \"con_toi_bi_sot\"}}]": "utter_con_toi_bi_sot",
      "[{\"prev_action\": {\"action_name\": \"action_listen\"}, \"user\": {\"intent\": \"con_toi_bi_sot\"}}, {\"prev_action\": {\"action_name\": \"utter_con_toi_bi_sot\"}, \"user\": {\"intent\": \"con_toi_bi_sot\"}}]": "action_listen",
      "[{\"prev_action\": {\"action_name\": \"action_listen\"}, \"user\": {\"intent\": \"lam_duoc_nhung_gi\"}}]": "utter_lam_duoc_nhung_gi",
      "[{\"prev_action\": {\"action_name\": \"action_listen\"}, \"user\": {\"intent\": \"lam_duoc_nhung_gi\"}}, {\"prev_action\": {\"action_name\": \"utter_lam_duoc_nhung_gi\"}, \"user\": {\"intent\": \"lam_duoc_nhung_gi\"}}]": "action_listen",
      "[{\"prev_action\": {\"action_name\": \"action_listen\"}, \"user\": {\"intent\": \"toi_muon_noi_soi_da_day\"}}]": "utter_toi_muon_noi_soi_da_day",
      "[{\"prev_action\": {\"action_name\": \"action_listen\"}, \"user\": {\"intent\": \"toi_muon_noi_soi_da_day\"}}, {\"prev_action\": {\"action_name\": \"utter_toi_muon_noi_soi_da_day\"}, \"user\": {\"intent\": \"toi_muon_noi_soi_da_day\"}}]": "action_listen",
      "[{\"prev_action\": {\"action_name\": \"action_listen\"}, \"user\": {\"intent\": \"Sieu_thi_o_dau?\"}}]": "utter_Sieu_thi_o_dau?",
      "[{\"prev_action\": {\"action_name\": \"action_listen\"}, \"user\": {\"intent\": \"Sieu_thi_o_dau?\"}}, {\"prev_action\": {\"action_name\": \"utter_Sieu_thi_o_dau?\"}, \"user\": {\"intent\": \"Sieu_thi_o_dau?\"}}]": "action_listen",
      "[{\"prev_action\": {\"action_name\": \"action_listen\"}, \"user\": {\"intent\": \"Kham_Co_xuong_khop_thuong_o_dau?\"}}]": "utter_Kham_Co_xuong_khop_thuong_o_dau?",
      "[{\"prev_action\": {\"action_name\": \"action_listen\"}, \"user\": {\"intent\": \"Kham_Co_xuong_khop_thuong_o_dau?\"}}, {\"prev_action\": {\"action_name\": \"utter_Kham_Co_xuong_khop_thuong_o_dau?\"}, \"user\": {\"intent\": \"Kham_Co_xuong_khop_thuong_o_dau?\"}}]": "action_listen",
      "[{\"prev_action\": {\"action_name\": \"action_listen\"}, \"user\": {\"intent\": \"Kham_co_xuong_khop_thac_si_o_dau?\"}}]": "utter_Kham_co_xuong_khop_thac_si_o_dau?",
      "[{\"prev_action\": {\"action_name\": \"action_listen\"}, \"user\": {\"intent\": \"Kham_co_xuong_khop_thac_si_o_dau?\"}}, {\"prev_action\": {\"action_name\": \"utter_Kham_co_xuong_khop_thac_si_o_dau?\"}, \"user\": {\"intent\": \"Kham_co_xuong_khop_thac_si_o_dau?\"}}]": "action_listen",
      "[{\"prev_action\": {\"action_name\": \"action_listen\"}, \"user\": {\"intent\": \"toi_bi_dau_rang\"}}]": "utter_toi_bi_dau_rang",
      "[{\"prev_action\": {\"action_name\": \"action_listen\"}, \"user\": {\"intent\": \"toi_bi_dau_rang\"}}, {\"prev_action\": {\"action_name\": \"utter_toi_bi_dau_rang\"}, \"user\": {\"intent\": \"toi_bi_dau_rang\"}}]": "action_listen",
      "[{\"prev_action\": {\"action_name\": \"action_listen\"}, \"user\": {\"intent\": \"Kham_co_xuong_khop_pho_giao_su_o_dau?\"}}]": "utter_Kham_co_xuong_khop_pho_giao_su_o_dau?",
      "[{\"prev_action\": {\"action_name\": \"action_listen\"}, \"user\": {\"intent\": \"Kham_co_xuong_khop_pho_giao_su_o_dau?\"}}, {\"prev_action\": {\"action_name\": \"utter_Kham_co_xuong_khop_pho_giao_su_o_dau?\"}, \"user\": {\"intent\": \"Kham_co_xuong_khop_pho_giao_su_o_dau?\"}}]": "action_listen",
      "[{\"prev_action\": {\"action_name\": \"action_listen\"}, \"user\": {\"intent\": \"Theo_doi_ket_qua_kham_tren_dien_thoai_nhu_the_nao?\"}}]": "utter_Theo_doi_ket_qua_kham_tren_dien_thoai_nhu_the_nao?",
      "[{\"prev_action\": {\"action_name\": \"action_listen\"}, \"user\": {\"intent\": \"Theo_doi_ket_qua_kham_tren_dien_thoai_nhu_the_nao?\"}}, {\"prev_action\": {\"action_name\": \"utter_Theo_doi_ket_qua_kham_tren_dien_thoai_nhu_the_nao?\"}, \"user\": {\"intent\": \"Theo_doi_ket_qua_kham_tren_dien_thoai_nhu_the_nao?\"}}]": "action_listen",
      "[{\"prev_action\": {\"action_name\": \"action_listen\"}, \"user\": {\"intent\": \"kiem_tra_suc_khoe_dinh_ky\"}}]": "utter_kiem_tra_suc_khoe_dinh_ky",
      "[{\"prev_action\": {\"action_name\": \"action_listen\"}, \"user\": {\"intent\": \"kiem_tra_suc_khoe_dinh_ky\"}}, {\"prev_action\": {\"action_name\": \"utter_kiem_tra_suc_khoe_dinh_ky\"}, \"user\": {\"intent\": \"kiem_tra_suc_khoe_dinh_ky\"}}]": "action_listen",
      "[{\"prev_action\": {\"action_name\": \"action_listen\"}, \"user\": {\"intent\": \"Khoa_kiem_soat_nhiem_khuan_o_dau?\"}}]": "utter_Khoa_kiem_soat_nhiem_khuan_o_dau?",
      "[{\"prev_action\": {\"action_name\": \"action_listen\"}, \"user\": {\"intent\": \"Khoa_kiem_soat_nhiem_khuan_o_dau?\"}}, {\"prev_action\": {\"action_name\": \"utter_Khoa_kiem_soat_nhiem_khuan_o_dau?\"}, \"user\": {\"intent\": \"Khoa_kiem_soat_nhiem_khuan_o_dau?\"}}]": "action_listen",
      "[{\"prev_action\": {\"action_name\": \"action_listen\"}, \"user\": {\"intent\": \"Dang_ky_su_dung_the_khach_hang_nhu_the_nao?\"}}]": "utter_Dang_ky_su_dung_the_khach_hang_nhu_the_nao?",
      "[{\"prev_action\": {\"action_name\": \"action_listen\"}, \"user\": {\"intent\": \"Dang_ky_su_dung_the_khach_hang_nhu_the_nao?\"}}, {\"prev_action\": {\"action_name\": \"utter_Dang_ky_su_dung_the_khach_hang_nhu_the_nao?\"}, \"user\": {\"intent\": \"Dang_ky_su_dung_the_khach_hang_nhu_the_nao?\"}}]": "action_listen",
      "[{\"prev_action\": {\"action_name\": \"action_listen\"}, \"user\": {\"intent\": \"Nha_I\"}}]": "utter_Nha_I",
      "[{\"prev_action\": {\"action_name\": \"action_listen\"}, \"user\": {\"intent\": \"Nha_I\"}}, {\"prev_action\": {\"action_name\": \"utter_Nha_I\"}, \"user\": {\"intent\": \"Nha_I\"}}]": "action_listen",
      "[{\"prev_action\": {\"action_name\": \"action_listen\"}, \"user\": {\"intent\": \"Tam_ung_tien\"}}]": "utter_Tam_ung_tien",
      "[{\"prev_action\": {\"action_name\": \"action_listen\"}, \"user\": {\"intent\": \"Tam_ung_tien\"}}, {\"prev_action\": {\"action_name\": \"utter_Tam_ung_tien\"}, \"user\": {\"intent\": \"Tam_ung_tien\"}}]": "action_listen",
      "[{\"prev_action\": {\"action_name\": \"action_listen\"}, \"user\": {\"intent\": \"Khoa_Co_xuong_khop_o_dau?\"}}]": "utter_Khoa_Co_xuong_khop_o_dau?",
      "[{\"prev_action\": {\"action_name\": \"action_listen\"}, \"user\": {\"intent\": \"Khoa_Co_xuong_khop_o_dau?\"}}, {\"prev_action\": {\"action_name\": \"utter_Khoa_Co_xuong_khop_o_dau?\"}, \"user\": {\"intent\": \"Khoa_Co_xuong_khop_o_dau?\"}}]": "action_listen",
      "[{\"prev_action\": {\"action_name\": \"action_listen\"}, \"user\": {\"intent\": \"gioi_thieu_cong_ty\"}}]": "utter_gioi_thieu_cong_ty",
      "[{\"prev_action\": {\"action_name\": \"action_listen\"}, \"user\": {\"intent\": \"gioi_thieu_cong_ty\"}}, {\"prev_action\": {\"action_name\": \"utter_gioi_thieu_cong_ty\"}, \"user\": {\"intent\": \"gioi_thieu_cong_ty\"}}]": "action_listen",
      "[{\"prev_action\": {\"action_name\": \"action_listen\"}, \"user\": {\"intent\": \"Nha_H\"}}]": "utter_Nha_H",
      "[{\"prev_action\": {\"action_name\": \"action_listen\"}, \"user\": {\"intent\": \"Nha_H\"}}, {\"prev_action\": {\"action_name\": \"utter_Nha_H\"}, \"user\": {\"intent\": \"Nha_H\"}}]": "action_listen",
      "[{\"prev_action\": {\"action_name\": \"action_listen\"}, \"user\": {\"intent\": \"hoi_ve_thoi_tiet\"}}]": "utter_hoi_ve_thoi_tiet",
      "[{\"prev_action\": {\"action_name\": \"action_listen\"}, \"user\": {\"intent\": \"hoi_ve_thoi_tiet\"}}, {\"prev_action\": {\"action_name\": \"utter_hoi_ve_thoi_tiet\"}, \"user\": {\"intent\": \"hoi_ve_thoi_tiet\"}}]": "action_listen",
      "[{\"prev_action\": {\"action_name\": \"action_listen\"}, \"user\": {\"intent\": \"Khoa_mat_o_dau?\"}}]": "utter_Khoa_mat_o_dau?",
      "[{\"prev_action\": {\"action_name\": \"action_listen\"}, \"user\": {\"intent\": \"Khoa_mat_o_dau?\"}}, {\"prev_action\": {\"action_name\": \"utter_Khoa_mat_o_dau?\"}, \"user\": {\"intent\": \"Khoa_mat_o_dau?\"}}]": "action_listen",
      "[{\"prev_action\": {\"action_name\": \"action_listen\"}, \"user\": {\"intent\": \"toi_bi_ngua\"}}]": "utter_toi_bi_ngua",
      "[{\"prev_action\": {\"action_name\": \"action_listen\"}, \"user\": {\"intent\": \"toi_bi_ngua\"}}, {\"prev_action\": {\"action_name\": \"utter_toi_bi_ngua\"}, \"user\": {\"intent\": \"toi_bi_ngua\"}}]": "action_listen",
      "[{\"prev_action\": {\"action_name\": \"action_listen\"}, \"user\": {\"intent\": \"Dang_ky_dich_vu_tiem_chung_o_dau?\"}}]": "utter_Dang_ky_dich_vu_tiem_chung_o_dau?",
      "[{\"prev_action\": {\"action_name\": \"action_listen\"}, \"user\": {\"intent\": \"Dang_ky_dich_vu_tiem_chung_o_dau?\"}}, {\"prev_action\": {\"action_name\": \"utter_Dang_ky_dich_vu_tiem_chung_o_dau?\"}, \"user\": {\"intent\": \"Dang_ky_dich_vu_tiem_chung_o_dau?\"}}]": "action_listen",
      "[{\"prev_action\": {\"action_name\": \"action_listen\"}, \"user\": {\"intent\": \"Nha_an_benh_vien_o_dau?\"}}]": "utter_Nha_an_benh_vien_o_dau?",
      "[{\"prev_action\": {\"action_name\": \"action_listen\"}, \"user\": {\"intent\": \"Nha_an_benh_vien_o_dau?\"}}, {\"prev_action\": {\"action_name\": \"utter_Nha_an_benh_vien_o_dau?\"}, \"user\": {\"intent\": \"Nha_an_benh_vien_o_dau?\"}}]": "action_listen",
      "[{\"prev_action\": {\"action_name\": \"action_listen\"}, \"user\": {\"intent\": \"Phong_kham_Nhi_o_dau?\"}}]": "utter_Phong_kham_Nhi_o_dau?",
      "[{\"prev_action\": {\"action_name\": \"action_listen\"}, \"user\": {\"intent\": \"Phong_kham_Nhi_o_dau?\"}}, {\"prev_action\": {\"action_name\": \"utter_Phong_kham_Nhi_o_dau?\"}, \"user\": {\"intent\": \"Phong_kham_Nhi_o_dau?\"}}]": "action_listen",
      "[{\"prev_action\": {\"action_name\": \"action_listen\"}, \"user\": {\"intent\": \"toi_bi_ho\"}}]": "utter_toi_bi_ho",
      "[{\"prev_action\": {\"action_name\": \"action_listen\"}, \"user\": {\"intent\": \"toi_bi_ho\"}}, {\"prev_action\": {\"action_name\": \"utter_toi_bi_ho\"}, \"user\": {\"intent\": \"toi_bi_ho\"}}]": "action_listen",
      "[{\"prev_action\": {\"action_name\": \"action_listen\"}, \"user\": {\"intent\": \"Thu_tuc_nhap_vien\"}}]": "utter_Thu_tuc_nhap_vien",
      "[{\"prev_action\": {\"action_name\": \"action_listen\"}, \"user\": {\"intent\": \"Thu_tuc_nhap_vien\"}}, {\"prev_action\": {\"action_name\": \"utter_Thu_tuc_nhap_vien\"}, \"user\": {\"intent\": \"Thu_tuc_nhap_vien\"}}]": "action_listen",
      "[{\"prev_action\": {\"action_name\": \"action_listen\"}, \"user\": {\"intent\": \"Khoa_sinh_hoa_o_dau?\"}}]": "utter_Khoa_sinh_hoa_o_dau?",
      "[{\"prev_action\": {\"action_name\": \"action_listen\"}, \"user\": {\"intent\": \"Khoa_sinh_hoa_o_dau?\"}}, {\"prev_action\": {\"action_name\": \"utter_Khoa_sinh_hoa_o_dau?\"}, \"user\": {\"intent\": \"Khoa_sinh_hoa_o_dau?\"}}]": "action_listen",
      "[{\"prev_action\": {\"action_name\": \"action_listen\"}, \"user\": {\"intent\": \"tam_biet\"}}]": "utter_tam_biet",
      "[{\"prev_action\": {\"action_name\": \"action_listen\"}, \"user\": {\"intent\": \"tam_biet\"}}, {\"prev_action\": {\"action_name\": \"utter_tam_biet\"}, \"user\": {\"intent\": \"tam_biet\"}}]": "action_listen",
      "[{\"prev_action\": {\"action_name\": \"action_listen\"}, \"user\": {\"intent\": \"Khoa_duoc_o_dau?\"}}]": "utter_Khoa_duoc_o_dau?",
      "[{\"prev_action\": {\"action_name\": \"action_listen\"}, \"user\": {\"intent\": \"Khoa_duoc_o_dau?\"}}, {\"prev_action\": {\"action_name\": \"utter_Khoa_duoc_o_dau?\"}, \"user\": {\"intent\": \"Khoa_duoc_o_dau?\"}}]": "action_listen",
      "[{\"prev_action\": {\"action_name\": \"action_listen\"}, \"user\": {\"intent\": \"nlu_fallback\"}}]": "utter_please_rephrase",
      "[{\"prev_action\": {\"action_name\": \"action_listen\"}, \"user\": {\"intent\": \"nlu_fallback\"}}, {\"prev_action\": {\"action_name\": \"utter_please_rephrase\"}, \"user\": {\"intent\": \"nlu_fallback\"}}]": "action_listen",
      "[{\"prev_action\": {\"action_name\": \"action_listen\"}, \"user\": {\"intent\": \"Khoa_hoi_suc_tich_cuc_o_dau?\"}}]": "utter_Khoa_hoi_suc_tich_cuc_o_dau?",
      "[{\"prev_action\": {\"action_name\": \"action_listen\"}, \"user\": {\"intent\": \"Khoa_hoi_suc_tich_cuc_o_dau?\"}}, {\"prev_action\": {\"action_name\": \"utter_Khoa_hoi_suc_tich_cuc_o_dau?\"}, \"user\": {\"intent\": \"Khoa_hoi_suc_tich_cuc_o_dau?\"}}]": "action_listen",
      "[{\"prev_action\": {\"action_name\": \"action_listen\"}, \"user\": {\"intent\": \"Phong_tai_chinh_ke_toan__o_dau?\"}}]": "utter_Phong_tai_chinh_ke_toan__o_dau?",
      "[{\"prev_action\": {\"action_name\": \"action_listen\"}, \"user\": {\"intent\": \"Phong_tai_chinh_ke_toan__o_dau?\"}}, {\"prev_action\": {\"action_name\": \"utter_Phong_tai_chinh_ke_toan__o_dau?\"}, \"user\": {\"intent\": \"Phong_tai_chinh_ke_toan__o_dau?\"}}]": "action_listen",
      "[{\"prev_action\": {\"action_name\": \"action_listen\"}, \"user\": {\"intent\": \"Quan_ca_phe_o_dau?\"}}]": "utter_Quan_ca_phe_o_dau?",
      "[{\"prev_action\": {\"action_name\": \"action_listen\"}, \"user\": {\"intent\": \"Quan_ca_phe_o_dau?\"}}, {\"prev_action\": {\"action_name\": \"utter_Quan_ca_phe_o_dau?\"}, \"user\": {\"intent\": \"Quan_ca_phe_o_dau?\"}}]": "action_listen",
      "[{\"prev_action\": {\"action_name\": \"action_listen\"}, \"user\": {\"intent\": \"Cay_ATM_o_dau?\"}}]": "utter_Cay_ATM_o_dau?",
      "[{\"prev_action\": {\"action_name\": \"action_listen\"}, \"user\": {\"intent\": \"Cay_ATM_o_dau?\"}}, {\"prev_action\": {\"action_name\": \"utter_Cay_ATM_o_dau?\"}, \"user\": {\"intent\": \"Cay_ATM_o_dau?\"}}]": "action_listen",
      "[{\"prev_action\": {\"action_name\": \"action_listen\"}, \"user\": {\"intent\": \"toi_bi_ngat_mui\"}}]": "utter_toi_bi_ngat_mui",
      "[{\"prev_action\": {\"action_name\": \"action_listen\"}, \"user\": {\"intent\": \"toi_bi_ngat_mui\"}}, {\"prev_action\": {\"action_name\": \"utter_toi_bi_ngat_mui\"}, \"user\": {\"intent\": \"toi_bi_ngat_mui\"}}]": "action_listen",
      "[{\"prev_action\": {\"action_name\": \"action_listen\"}, \"user\": {\"intent\": \"di_choi_khong\"}}]": "utter_di_choi_khong",
      "[{\"prev_action\": {\"action_name\": \"action_listen\"}, \"user\": {\"intent\": \"di_choi_khong\"}}, {\"prev_action\": {\"action_name\": \"utter_di_choi_khong\"}, \"user\": {\"intent\": \"di_choi_khong\"}}]": "action_listen",
      "[{\"prev_action\": {\"action_name\": \"action_listen\"}, \"user\": {\"intent\": \"toi_bi_dau_dau\"}}]": "utter_toi_bi_dau_dau",
      "[{\"prev_action\": {\"action_name\": \"action_listen\"}, \"user\": {\"intent\": \"toi_bi_dau_dau\"}}, {\"prev_action\": {\"action_name\": \"utter_toi_bi_dau_dau\"}, \"user\": {\"intent\": \"toi_bi_dau_dau\"}}]": "action_listen",
      "[{\"prev_action\": {\"action_name\": \"action_listen\"}, \"user\": {\"intent\": \"Khoa_phau_thuat_than_tiet_nieu_&_nam_hoc_o_dau?\"}}]": "utter_Khoa_phau_thuat_than_tiet_nieu_&_nam_hoc_o_dau?",
      "[{\"prev_action\": {\"action_name\": \"action_listen\"}, \"user\": {\"intent\": \"Khoa_phau_thuat_than_tiet_nieu_&_nam_hoc_o_dau?\"}}, {\"prev_action\": {\"action_name\": \"utter_Khoa_phau_thuat_than_tiet_nieu_&_nam_hoc_o_dau?\"}, \"user\": {\"intent\": \"Khoa_phau_thuat_than_tiet_nieu_&_nam_hoc_o_dau?\"}}]": "action_listen",
      "[{\"prev_action\": {\"action_name\": \"action_listen\"}, \"user\": {\"intent\": \"Khoa_phuc_hoi_chuc_nang_o_dau?\"}}]": "utter_Khoa_phuc_hoi_chuc_nang_o_dau?",
      "[{\"prev_action\": {\"action_name\": \"action_listen\"}, \"user\": {\"intent\": \"Khoa_phuc_hoi_chuc_nang_o_dau?\"}}, {\"prev_action\": {\"action_name\": \"utter_Khoa_phuc_hoi_chuc_nang_o_dau?\"}, \"user\": {\"intent\": \"Khoa_phuc_hoi_chuc_nang_o_dau?\"}}]": "action_listen"
    },
    "rule_only_slots": [],
    "rule_only_loops": [],
    "rules_for_loop_unhappy_path": {},
    "rules_not_in_stories": [
      "[{\"prev_action\": {\"action_name\": \"action_listen\"}, \"user\": {\"intent\": \"khen_chatbot\"}}, {\"prev_action\": {\"action_name\": \"utter_khen_chatbot\"}, \"user\": {\"intent\": \"khen_chatbot\"}}]",
      "[{\"prev_action\": {\"action_name\": \"action_listen\"}, \"user\": {\"intent\": \"Khoa_benh_nhiet_doi_o_dau?\"}}]",
      "[{\"prev_action\": {\"action_name\": \"action_listen\"}, \"user\": {\"intent\": \"di_choi_khong\"}}, {\"prev_action\": {\"action_name\": \"utter_di_choi_khong\"}, \"user\": {\"intent\": \"di_choi_khong\"}}]",
      "[{\"prev_action\": {\"action_name\": \"action_listen\"}, \"user\": {\"intent\": \"Thanh_toan_BHYT_o_dau?\"}}]",
      "[{\"prev_action\": {\"action_name\": \"action_listen\"}, \"user\": {\"intent\": \"Khoa_huyet_hoc_o_dau?\"}}]",
      "[{\"prev_action\": {\"action_name\": \"action_listen\"}, \"user\": {\"intent\": \"Thu_ngan_o_dau?\"}}, {\"prev_action\": {\"action_name\": \"utter_Thu_ngan_o_dau?\"}, \"user\": {\"intent\": \"Thu_ngan_o_dau?\"}}]",
      "[{\"prev_action\": {\"action_name\": \"action_listen\"}, \"user\": {\"intent\": \"Nha_thuoc_benh_vien_o_dau?\"}}, {\"prev_action\": {\"action_name\": \"utter_Nha_thuoc_benh_vien_o_dau?\"}, \"user\": {\"intent\": \"Nha_thuoc_benh_vien_o_dau?\"}}]",
      "[{\"prev_action\": {\"action_name\": \"action_listen\"}, \"user\": {\"intent\": \"Thanh_toan_BHYT_o_dau?\"}}, {\"prev_action\": {\"action_name\": \"utter_Thanh_toan_BHYT_o_dau?\"}, \"user\": {\"intent\": \"Thanh_toan_BHYT_o_dau?\"}}]",
      "[{\"prev_action\": {\"action_name\": \"action_listen\"}, \"user\": {\"intent\": \"Khoa_ung_buou_o_dau?\"}}, {\"prev_action\": {\"action_name\": \"utter_Khoa_ung_buou_o_dau?\"}, \"user\": {\"intent\": \"Khoa_ung_buou_o_dau?\"}}]",
      "[{\"prev_action\": {\"action_name\": \"action_listen\"}, \"user\": {\"intent\": \"toi_bi_nga_xe\"}}, {\"prev_action\": {\"action_name\": \"utter_toi_bi_nga_xe\"}, \"user\": {\"intent\": \"toi_bi_nga_xe\"}}]",
      "[{\"prev_action\": {\"action_name\": \"action_listen\"}, \"user\": {\"intent\": \"Quan_ca_phe_o_dau?\"}}, {\"prev_action\": {\"action_name\": \"utter_Quan_ca_phe_o_dau?\"}, \"user\": {\"intent\": \"Quan_ca_phe_o_dau?\"}}]",
      "[{\"prev_action\": {\"action_name\": \"action_listen\"}, \"user\": {\"intent\": \"Khoa_vi_sinh_o_dau?\"}}]",
      "[{\"prev_action\": {\"action_name\": \"action_listen\"}, \"user\": {\"intent\": \"cam_on\"}}]",
      "[{\"prev_action\": {\"action_name\": \"action_listen\"}, \"user\": {\"intent\": \"Khoa_than_tiet_nieu_va_loc_mau_o_dau?\"}}, {\"prev_action\": {\"action_name\": \"utter_Khoa_than_tiet_nieu_va_loc_mau_o_dau?\"}, \"user\": {\"intent\": \"Khoa_than_tiet_nieu_va_loc_mau_o_dau?\"}}]",
      "[{\"prev_action\": {\"action_name\": \"action_listen\"}, \"user\": {\"intent\": \"Nha_B\"}}, {\"prev_action\": {\"action_name\": \"utter_Nha_B\"}, \"user\": {\"intent\": \"Nha_B\"}}]",
      "[{\"prev_action\": {\"action_name\": \"action_listen\"}, \"user\": {\"intent\": \"Kham_co_xuong_khop_tien_si_o_dau?\"}}]",
      "[{\"prev_action\": {\"action_name\": \"action_listen\"}, \"user\": {\"intent\": \"con_toi_bi_sot\"}}, {\"prev_action\": {\"action_name\": \"utter_con_toi_bi_sot\"}, \"user\": {\"intent\": \"con_toi_bi_sot\"}}]",
      "[{\"prev_action\": {\"action_name\": \"action_listen\"}, \"user\": {\"intent\": \"Nha_tang_le_benh_vien_E_o_dau?\"}}]",
      "[{\"prev_action\": {\"action_name\": \"action_listen\"}, \"user\": {\"intent\": \"toi_bi_dau_xuong_khop\"}}]",
      "[{\"prev_action\": {\"action_name\": \"action_listen\"}, \"user\": {\"intent\": \"nlu_fallback\"}}]",
      "[{\"prev_action\": {\"action_name\": \"action_listen\"}, \"user\": {\"intent\": \"Khoa_noi_than_kinh_o_dau?\"}}]",
      "[{\"prev_action\": {\"action_name\": \"action_listen\"}, \"user\": {\"intent\": \"Khoa_than_nhan_tao_o_dau?\"}}, {\"prev_action\": {\"action_name\": \"utter_Khoa_than_nhan_tao_o_dau?\"}, \"user\": {\"intent\": \"Khoa_than_nhan_tao_o_dau?\"}}]",
      "[{\"prev_action\": {\"action_name\": \"action_listen\"}, \"user\": {\"intent\": \"toi_di_kham_thai\"}}]",
      "[{\"prev_action\": {\"action_name\": \"action_listen\"}, \"user\": {\"intent\": \"Dang_ky_dich_vu_tiem_chung_o_dau?\"}}]",
      "[{\"prev_action\": {\"action_name\": \"action_listen\"}, \"user\": {\"intent\": \"hoi_ve_thoi_tiet\"}}, {\"prev_action\": {\"action_name\": \"utter_hoi_ve_thoi_tiet\"}, \"user\": {\"intent\": \"hoi_ve_thoi_tiet\"}}]",
      "[{\"prev_action\": {\"action_name\": \"action_listen\"}, \"user\": {\"intent\": \"Khoa_huyet_hoc_o_dau?\"}}, {\"prev_action\": {\"action_name\": \"utter_Khoa_huyet_hoc_o_dau?\"}, \"user\": {\"intent\": \"Khoa_huyet_hoc_o_dau?\"}}]",
      "[{\"prev_action\": {\"action_name\": \"action_listen\"}, \"user\": {\"intent\": \"Phong_tai_chinh_ke_toan__o_dau?\"}}, {\"prev_action\": {\"action_name\": \"utter_Phong_tai_chinh_ke_toan__o_dau?\"}, \"user\": {\"intent\": \"Phong_tai_chinh_ke_toan__o_dau?\"}}]",
      "[{\"prev_action\": {\"action_name\": \"action_listen\"}, \"user\": {\"intent\": \"di_choi_khong\"}}]",
      "[{\"prev_action\": {\"action_name\": \"action_listen\"}, \"user\": {\"intent\": \"hoi_ve_thoi_tiet\"}}]",
      "[{\"prev_action\": {\"action_name\": \"action_listen\"}, \"user\": {\"intent\": \"Lay_mau_o_dau?\"}}]",
      "[{\"prev_action\": {\"action_name\": \"action_listen\"}, \"user\": {\"intent\": \"gioi_thieu_cong_ty\"}}, {\"prev_action\": {\"action_name\": \"utter_gioi_thieu_cong_ty\"}, \"user\": {\"intent\": \"gioi_thieu_cong_ty\"}}]",
      "[{\"prev_action\": {\"action_name\": \"action_listen\"}, \"user\": {\"intent\": \"Khoa_mat_o_dau?\"}}]",
      "[{\"prev_action\": {\"action_name\": \"action_listen\"}, \"user\": {\"intent\": \"Khoa_tieu_hoa_o_dau?\"}}]",
      "[{\"prev_action\": {\"action_name\": \"action_listen\"}, \"user\": {\"intent\": \"Khoa_tim_mach_o_dau?\"}}]",
      "[{\"prev_action\": {\"action_name\": \"action_listen\"}, \"user\": {\"intent\": \"Khoa_benh_nhiet_doi_o_dau?\"}}, {\"prev_action\": {\"action_name\": \"utter_Khoa_benh_nhiet_doi_o_dau?\"}, \"user\": {\"intent\": \"Khoa_benh_nhiet_doi_o_dau?\"}}]",
      "[{\"prev_action\": {\"action_name\": \"action_listen\"}, \"user\": {\"intent\": \"Khoa_kham_benh_o_dau\"}}, {\"prev_action\": {\"action_name\": \"utter_Khoa_kham_benh_o_dau\"}, \"user\": {\"intent\": \"Khoa_kham_benh_o_dau\"}}]",
      "[{\"prev_action\": {\"action_name\": \"action_listen\"}, \"user\": {\"intent\": \"kiem_tra_suc_khoe_dinh_ky\"}}]",
      "[{\"prev_action\": {\"action_name\": \"action_listen\"}, \"user\": {\"intent\": \"toi_bi_ngua\"}}]",
      "[{\"prev_action\": {\"action_name\": \"action_listen\"}, \"user\": {\"intent\": \"Khoa_noi_gan_mat_o_dau?\"}}]",
      "[{\"prev_action\": {\"action_name\": \"action_listen\"}, \"user\": {\"intent\": \"Khoa_ho_hap_o_dau?\"}}]",
      "[{\"prev_action\": {\"action_name\": \"action_listen\"}, \"user\": {\"intent\": \"Cay_ATM_o_dau?\"}}, {\"prev_action\": {\"action_name\": \"utter_Cay_ATM_o_dau?\"}, \"user\": {\"intent\": \"Cay_ATM_o_dau?\"}}]",
      "[{\"prev_action\": {\"action_name\": \"action_listen\"}, \"user\": {\"intent\": \"toi_bi_\\u0111au_tuc_nguc\"}}, {\"prev_action\": {\"action_name\": \"utter_toi_bi_dau_tuc_nguc\"}, \"user\": {\"intent\": \"toi_bi_\\u0111au_tuc_nguc\"}}]",
      "[{\"prev_action\": {\"action_name\": \"action_listen\"}, \"user\": {\"intent\": \"Khoa_y_hoc_co_truyen_o_dau?\"}}]",
      "[{\"prev_action\": {\"action_name\": \"action_listen\"}, \"user\": {\"intent\": \"Phong_kham_Nhi_o_dau?\"}}]",
      "[{\"prev_action\": {\"action_name\": \"action_listen\"}, \"user\": {\"intent\": \"Cay_ATM_o_dau?\"}}]",
      "[{\"prev_action\": {\"action_name\": \"action_listen\"}, \"user\": {\"intent\": \"hoi_tuoi_robot\"}}, {\"prev_action\": {\"action_name\": \"utter_hoi_tuoi_robot\"}, \"user\": {\"intent\": \"hoi_tuoi_robot\"}}]",
      "[{\"prev_action\": {\"action_name\": \"action_listen\"}, \"user\": {\"intent\": \"Khoa_hoi_suc_tich_cuc_o_dau?\"}}, {\"prev_action\": {\"action_name\": \"utter_Khoa_hoi_suc_tich_cuc_o_dau?\"}, \"user\": {\"intent\": \"Khoa_hoi_suc_tich_cuc_o_dau?\"}}]",
      "[{\"prev_action\": {\"action_name\": \"action_listen\"}, \"user\": {\"intent\": \"toi_bi_dau_dau\"}}]",
      "[{\"prev_action\": {\"action_name\": \"action_listen\"}, \"user\": {\"intent\": \"Kham_Co_xuong_khop_thuong_o_dau?\"}}, {\"prev_action\": {\"action_name\": \"utter_Kham_Co_xuong_khop_thuong_o_dau?\"}, \"user\": {\"intent\": \"Kham_Co_xuong_khop_thuong_o_dau?\"}}]",
      "[{\"prev_action\": {\"action_name\": \"action_listen\"}, \"user\": {\"intent\": \"Khoa_hoi_suc_tich_cuc_o_dau?\"}}]",
      "[{\"prev_action\": {\"action_name\": \"action_listen\"}, \"user\": {\"intent\": \"Giay_to_can_thiet_kham_la_gi?\"}}, {\"prev_action\": {\"action_name\": \"utter_Giay_to_can_thiet_kham_la_gi?\"}, \"user\": {\"intent\": \"Giay_to_can_thiet_kham_la_gi?\"}}]",
      "[{\"prev_action\": {\"action_name\": \"action_listen\"}, \"user\": {\"intent\": \"Khoa_than_nhan_tao_o_dau?\"}}]",
      "[{\"prev_action\": {\"action_name\": \"action_listen\"}, \"user\": {\"intent\": \"Khoa_dinh_duong_o_dau?\"}}]",
      "[{\"prev_action\": {\"action_name\": \"action_listen\"}, \"user\": {\"intent\": \"Khoa_Noi_nhi_tong_hop_o_dau?\"}}, {\"prev_action\": {\"action_name\": \"utter_Khoa_Noi_nhi_tong_hop_o_dau?\"}, \"user\": {\"intent\": \"Khoa_Noi_nhi_tong_hop_o_dau?\"}}]",
      "[{\"prev_action\": {\"action_name\": \"action_listen\"}, \"user\": {\"intent\": \"Nha_D\"}}]",
      "[{\"prev_action\": {\"action_name\": \"action_listen\"}, \"user\": {\"intent\": \"Nha_C\"}}]",
      "[{\"prev_action\": {\"action_name\": \"action_listen\"}, \"user\": {\"intent\": \"Khoa_duoc_o_dau?\"}}, {\"prev_action\": {\"action_name\": \"utter_Khoa_duoc_o_dau?\"}, \"user\": {\"intent\": \"Khoa_duoc_o_dau?\"}}]",
      "[{\"prev_action\": {\"action_name\": \"action_listen\"}, \"user\": {\"intent\": \"Khoa_kiem_soat_nhiem_khuan_o_dau?\"}}, {\"prev_action\": {\"action_name\": \"utter_Khoa_kiem_soat_nhiem_khuan_o_dau?\"}, \"user\": {\"intent\": \"Khoa_kiem_soat_nhiem_khuan_o_dau?\"}}]",
      "[{\"prev_action\": {\"action_name\": \"action_listen\"}, \"user\": {\"intent\": \"Phong_tai_chinh_ke_toan__o_dau?\"}}]",
      "[{\"prev_action\": {\"action_name\": \"action_listen\"}, \"user\": {\"intent\": \"Khoa_San_o_dau?\"}}]",
      "[{\"prev_action\": {\"action_name\": \"action_listen\"}, \"user\": {\"intent\": \"Dang_ky_dich_vu_tiem_chung_o_dau?\"}}, {\"prev_action\": {\"action_name\": \"utter_Dang_ky_dich_vu_tiem_chung_o_dau?\"}, \"user\": {\"intent\": \"Dang_ky_dich_vu_tiem_chung_o_dau?\"}}]",
      "[{\"prev_action\": {\"action_name\": \"action_listen\"}, \"user\": {\"intent\": \"Khoa_tim_mach_o_dau?\"}}, {\"prev_action\": {\"action_name\": \"utter_Khoa_tim_mach_o_dau?\"}, \"user\": {\"intent\": \"Khoa_tim_mach_o_dau?\"}}]",
      "[{\"prev_action\": {\"action_name\": \"action_listen\"}, \"user\": {\"intent\": \"Khoa_noi_tong_hop_o_dau?\"}}]",
      "[{\"prev_action\": {\"action_name\": \"action_listen\"}, \"user\": {\"intent\": \"toi_bi_\\u0111au_tuc_nguc\"}}]",
      "[{\"prev_action\": {\"action_name\": \"action_listen\"}, \"user\": {\"intent\": \"Khoa_chan_doan_hinh_anh_o_dau?\"}}, {\"prev_action\": {\"action_name\": \"utter_Khoa_chan_doan_hinh_anh_o_dau?\"}, \"user\": {\"intent\": \"Khoa_chan_doan_hinh_anh_o_dau?\"}}]",
      "[{\"prev_action\": {\"action_name\": \"action_listen\"}, \"user\": {\"intent\": \"gioi_thieu_cong_ty\"}}]",
      "[{\"prev_action\": {\"action_name\": \"action_listen\"}, \"user\": {\"intent\": \"Khoa_phau_thuat_-_gay_me_hoi_suc_o_dau?\"}}, {\"prev_action\": {\"action_name\": \"utter_Khoa_phau_thuat_-_gay_me_hoi_suc_o_dau?\"}, \"user\": {\"intent\": \"Khoa_phau_thuat_-_gay_me_hoi_suc_o_dau?\"}}]",
      "[{\"prev_action\": {\"action_name\": \"action_listen\"}, \"user\": {\"intent\": \"Khoa_mat_o_dau?\"}}, {\"prev_action\": {\"action_name\": \"utter_Khoa_mat_o_dau?\"}, \"user\": {\"intent\": \"Khoa_mat_o_dau?\"}}]",
      "[{\"prev_action\": {\"action_name\": \"action_listen\"}, \"user\": {\"intent\": \"Nha_I\"}}, {\"prev_action\": {\"action_name\": \"utter_Nha_I\"}, \"user\": {\"intent\": \"Nha_I\"}}]",
      "[{\"prev_action\": {\"action_name\": \"action_listen\"}, \"user\": {\"intent\": \"Phong_kham_ngoai_tong_hop_o_dau?\"}}, {\"prev_action\": {\"action_name\": \"utter_Phong_kham_ngoai_tong_hop_o_dau?\"}, \"user\": {\"intent\": \"Phong_kham_ngoai_tong_hop_o_dau?\"}}]",
      "[{\"prev_action\": {\"action_name\": \"action_listen\"}, \"user\": {\"intent\": \"Sieu_thi_o_dau?\"}}, {\"prev_action\": {\"action_name\": \"utter_Sieu_thi_o_dau?\"}, \"user\": {\"intent\": \"Sieu_thi_o_dau?\"}}]",
      "[{\"prev_action\": {\"action_name\": \"action_listen\"}, \"user\": {\"intent\": \"Nha_P\"}}]",
      "[{\"prev_action\": {\"action_name\": \"action_listen\"}, \"user\": {\"intent\": \"Khoa_Tai_mui_hong_o_dau\"}}, {\"prev_action\": {\"action_name\": \"utter_Khoa_Tai_mui_hong_o_dau\"}, \"user\": {\"intent\": \"Khoa_Tai_mui_hong_o_dau\"}}]",
      "[{\"prev_action\": {\"action_name\": \"action_listen\"}, \"user\": {\"intent\": \"toi_bi_dau_mat\"}}]",
      "[{\"prev_action\": {\"action_name\": \"action_listen\"}, \"user\": {\"intent\": \"toi_bi_dau_hong\"}}, {\"prev_action\": {\"action_name\": \"utter_toi_bi_dau_hong\"}, \"user\": {\"intent\": \"toi_bi_dau_hong\"}}]",
      "[{\"prev_action\": {\"action_name\": \"action_listen\"}, \"user\": {\"intent\": \"toi_bi_ho\"}}, {\"prev_action\": {\"action_name\": \"utter_toi_bi_ho\"}, \"user\": {\"intent\": \"toi_bi_ho\"}}]",
      "[{\"prev_action\": {\"action_name\": \"action_listen\"}, \"user\": {\"intent\": \"Em_muon_dang_ki_kham_theo_yeu_cau\"}}]",
      "[{\"prev_action\": {\"action_name\": \"action_listen\"}, \"user\": {\"intent\": \"Tra_so_BHYT_o_dau?\"}}, {\"prev_action\": {\"action_name\": \"utter_Tra_so_BHYT_o_dau?\"}, \"user\": {\"intent\": \"Tra_so_BHYT_o_dau?\"}}]",
      "[{\"prev_action\": {\"action_name\": \"action_listen\"}, \"user\": {\"intent\": \"hoi_an_chua\"}}]",
      "[{\"prev_action\": {\"action_name\": \"action_listen\"}, \"user\": {\"intent\": \"Khoa_Tai_mui_hong_o_dau\"}}]",
      "[{\"prev_action\": {\"action_name\": \"action_listen\"}, \"user\": {\"intent\": \"Khoa_ngoai_chan_thuong_o_dau?\"}}]",
      "[{\"prev_action\": {\"action_name\": \"action_listen\"}, \"user\": {\"intent\": \"kiem_tra_suc_khoe_dinh_ky\"}}, {\"prev_action\": {\"action_name\": \"utter_kiem_tra_suc_khoe_dinh_ky\"}, \"user\": {\"intent\": \"kiem_tra_suc_khoe_dinh_ky\"}}]",
      "[{\"prev_action\": {\"action_name\": \"action_listen\"}, \"user\": {\"intent\": \"Lay_mau_o_dau?\"}}, {\"prev_action\": {\"action_name\": \"utter_Lay_mau_o_dau?\"}, \"user\": {\"intent\": \"Lay_mau_o_dau?\"}}]",
      "[{\"prev_action\": {\"action_name\": \"action_listen\"}, \"user\": {\"intent\": \"toi_muon_noi_soi_da_day\"}}]",
      "[{\"prev_action\": {\"action_name\": \"action_listen\"}, \"user\": {\"intent\": \"toi_bi_di_ngoai\"}}, {\"prev_action\": {\"action_name\": \"utter_toi_bi_di_ngoai\"}, \"user\": {\"intent\": \"toi_bi_di_ngoai\"}}]",
      "[{\"prev_action\": {\"action_name\": \"action_listen\"}, \"user\": {\"intent\": \"Khoa_Rang_ham_mat_o_dau\"}}, {\"prev_action\": {\"action_name\": \"utter_Khoa_Rang_ham_mat_o_dau\"}, \"user\": {\"intent\": \"Khoa_Rang_ham_mat_o_dau\"}}]",
      "[{\"prev_action\": {\"action_name\": \"action_listen\"}, \"user\": {\"intent\": \"Kham_Co_xuong_khop_thuong_o_dau?\"}}]",
      "[{\"prev_action\": {\"action_name\": \"action_listen\"}, \"user\": {\"intent\": \"Dang_ky_su_dung_the_khach_hang_nhu_the_nao?\"}}]",
      "predicting default action with intent restart",
      "[{\"prev_action\": {\"action_name\": \"action_listen\"}, \"user\": {\"intent\": \"Khoa_tham_do_chuc_nang_-_noi_soi_o_dau?\"}}, {\"prev_action\": {\"action_name\": \"utter_Khoa_tham_do_chuc_nang_-_noi_soi_o_dau?\"}, \"user\": {\"intent\": \"Khoa_tham_do_chuc_nang_-_noi_soi_o_dau?\"}}]",
      "[{\"prev_action\": {\"action_name\": \"action_listen\"}, \"user\": {\"intent\": \"Nha_D\"}}, {\"prev_action\": {\"action_name\": \"utter_Nha_D\"}, \"user\": {\"intent\": \"Nha_D\"}}]",
      "[{\"prev_action\": {\"action_name\": \"action_listen\"}, \"user\": {\"intent\": \"Nha_an_benh_vien_o_dau?\"}}, {\"prev_action\": {\"action_name\": \"utter_Nha_an_benh_vien_o_dau?\"}, \"user\": {\"intent\": \"Nha_an_benh_vien_o_dau?\"}}]",
      "[{\"prev_action\": {\"action_name\": \"action_listen\"}, \"user\": {\"intent\": \"Khoa_ngoai_tong_hop_o_dau?\"}}]",
      "[{\"prev_action\": {\"action_name\": \"action_listen\"}, \"user\": {\"intent\": \"tam_biet\"}}]",
      "[{\"prev_action\": {\"action_name\": \"action_listen\"}, \"user\": {\"intent\": \"toi_bi_dau_mat\"}}, {\"prev_action\": {\"action_name\": \"utter_toi_bi_dau_mat\"}, \"user\": {\"intent\": \"toi_bi_dau_mat\"}}]",
      "[{\"prev_action\": {\"action_name\": \"action_listen\"}, \"user\": {\"intent\": \"Khoa_duoc_o_dau?\"}}]",
      "[{\"prev_action\": {\"action_name\": \"action_listen\"}, \"user\": {\"intent\": \"Khoa_phuc_hoi_chuc_nang_o_dau?\"}}]",
      "[{\"prev_action\": {\"action_name\": \"action_listen\"}, \"user\": {\"intent\": \"Khoa_kham_benh_o_dau\"}}]",
      "[{\"prev_action\": {\"action_name\": \"action_listen\"}, \"user\": {\"intent\": \"Kham_co_xuong_khop_tien_si_o_dau?\"}}, {\"prev_action\": {\"action_name\": \"utter_Kham_co_xuong_khop_tien_si_o_dau?\"}, \"user\": {\"intent\": \"Kham_co_xuong_khop_tien_si_o_dau?\"}}]",
      "[{\"prev_action\": {\"action_name\": \"action_listen\"}, \"user\": {\"intent\": \"Theo_doi_ket_qua_kham_tren_dien_thoai_nhu_the_nao?\"}}]",
      "[{\"prev_action\": {\"action_name\": \"action_listen\"}, \"user\": {\"intent\": \"Khoa_Phau_thuat_than_kinh_o_dau?\"}}]",
      "[{\"prev_action\": {\"action_name\": \"action_listen\"}, \"user\": {\"intent\": \"Xin_dau_vao_don_thuoc_o_dau\"}}]",
      "[{\"prev_action\": {\"action_name\": \"action_listen\"}, \"user\": {\"intent\": \"Khoa_Kiem_tra_suc_khoe_o_dau?\"}}]",
      "[{\"prev_action\": {\"action_name\": \"action_listen\"}, \"user\": {\"intent\": \"Khoa_sinh_hoa_o_dau?\"}}, {\"prev_action\": {\"action_name\": \"utter_Khoa_sinh_hoa_o_dau?\"}, \"user\": {\"intent\": \"Khoa_sinh_hoa_o_dau?\"}}]",
      "[{\"prev_action\": {\"action_name\": \"action_listen\"}, \"user\": {\"intent\": \"Khoa_phau_thuat_-_gay_me_hoi_suc_o_dau?\"}}]",
      "[{\"prev_action\": {\"action_name\": \"action_listen\"}, \"user\": {\"intent\": \"Khoa_ho_hap_o_dau?\"}}, {\"prev_action\": {\"action_name\": \"utter_Khoa_ho_hap_o_dau?\"}, \"user\": {\"intent\": \"Khoa_ho_hap_o_dau?\"}}]",
      "[{\"prev_action\": {\"action_name\": \"action_listen\"}, \"user\": {\"intent\": \"Khoa_chan_doan_hinh_anh_o_dau?\"}}]",
      "[{\"prev_action\": {\"action_name\": \"action_listen\"}, \"user\": {\"intent\": \"Khoa_kiem_soat_nhiem_khuan_o_dau?\"}}]",
      "[{\"prev_action\": {\"action_name\": \"action_listen\"}, \"user\": {\"intent\": \"Xin_dau_vao_don_thuoc_o_dau\"}}, {\"prev_action\": {\"action_name\": \"utter_Xin_dau_vao_don_thuoc_o_dau\"}, \"user\": {\"intent\": \"Xin_dau_vao_don_thuoc_o_dau\"}}]",
      "[{\"prev_action\": {\"action_name\": \"action_listen\"}, \"user\": {\"intent\": \"Nha_luu_tru_benh_vien_o_dau?\"}}, {\"prev_action\": {\"action_name\": \"utter_Nha_luu_tru_benh_vien_o_dau?\"}, \"user\": {\"intent\": \"Nha_luu_tru_benh_vien_o_dau?\"}}]",
      "[{\"prev_action\": {\"action_name\": \"action_listen\"}, \"user\": {\"intent\": \"Thoi_gian_lam_viec_cua_benh_vien\"}}, {\"prev_action\": {\"action_name\": \"utter_Thoi_gian_lam_viec_cua_benh_vien\"}, \"user\": {\"intent\": \"Thoi_gian_lam_viec_cua_benh_vien\"}}]",
      "[{\"prev_action\": {\"action_name\": \"action_listen\"}, \"user\": {\"intent\": \"Khoa_phau_thuat_than_tiet_nieu_&_nam_hoc_o_dau?\"}}]",
      "[{\"prev_action\": {\"action_name\": \"action_listen\"}, \"user\": {\"intent\": \"Khoa_noi_gan_mat_o_dau?\"}}, {\"prev_action\": {\"action_name\": \"utter_Khoa_noi_gan_mat_o_dau?\"}, \"user\": {\"intent\": \"Khoa_noi_gan_mat_o_dau?\"}}]",
      "[{\"prev_action\": {\"action_name\": \"action_listen\"}, \"user\": {\"intent\": \"toi_bi_ngat_mui\"}}]",
      "[{\"prev_action\": {\"action_name\": \"action_listen\"}, \"user\": {\"intent\": \"Phong_ke_hoach_tong_hop_o_dau?\"}}]",
      "[{\"prev_action\": {\"action_name\": \"action_listen\"}, \"user\": {\"intent\": \"con_toi_bi_sot\"}}]",
      "[{\"prev_action\": {\"action_name\": \"action_listen\"}, \"user\": {\"intent\": \"lam_duoc_nhung_gi\"}}]",
      "[{\"prev_action\": {\"action_name\": \"action_listen\"}, \"user\": {\"intent\": \"Kham_co_xuong_khop_thac_si_o_dau?\"}}, {\"prev_action\": {\"action_name\": \"utter_Kham_co_xuong_khop_thac_si_o_dau?\"}, \"user\": {\"intent\": \"Kham_co_xuong_khop_thac_si_o_dau?\"}}]",
      "[{\"prev_action\": {\"action_name\": \"action_listen\"}, \"user\": {\"intent\": \"Nha_H\"}}]",
      "[{\"prev_action\": {\"action_name\": \"action_listen\"}, \"user\": {\"intent\": \"toi_bi_dau_tai\"}}, {\"prev_action\": {\"action_name\": \"utter_toi_bi_dau_tai\"}, \"user\": {\"intent\": \"toi_bi_dau_tai\"}}]",
      "[{\"prev_action\": {\"action_name\": \"action_listen\"}, \"user\": {\"intent\": \"Phong_kham_Nhi_o_dau?\"}}, {\"prev_action\": {\"action_name\": \"utter_Phong_kham_Nhi_o_dau?\"}, \"user\": {\"intent\": \"Phong_kham_Nhi_o_dau?\"}}]",
      "[{\"prev_action\": {\"action_name\": \"action_listen\"}, \"user\": {\"intent\": \"Nha_tang_le_benh_vien_E_o_dau?\"}}, {\"prev_action\": {\"action_name\": \"utter_Nha_tang_le_benh_vien_E_o_dau?\"}, \"user\": {\"intent\": \"Nha_tang_le_benh_vien_E_o_dau?\"}}]",
      "[{\"prev_action\": {\"action_name\": \"action_listen\"}, \"user\": {\"intent\": \"Khoa_dinh_duong_o_dau?\"}}, {\"prev_action\": {\"action_name\": \"utter_Khoa_dinh_duong_o_dau?\"}, \"user\": {\"intent\": \"Khoa_dinh_duong_o_dau?\"}}]",
      "[{\"prev_action\": {\"action_name\": \"action_listen\"}, \"user\": {\"intent\": \"Khoa_Phau_thuat_than_kinh_o_dau?\"}}, {\"prev_action\": {\"action_name\": \"utter_Khoa_Phau_thuat_than_kinh_o_dau?\"}, \"user\": {\"intent\": \"Khoa_Phau_thuat_than_kinh_o_dau?\"}}]",
      "[{\"prev_action\": {\"action_name\": \"action_listen\"}, \"user\": {\"intent\": \"Photo_giay_to_o_dau?\"}}, {\"prev_action\": {\"action_name\": \"utter_Photo_giay_to_o_dau?\"}, \"user\": {\"intent\": \"Photo_giay_to_o_dau?\"}}]",
      "[{\"prev_action\": {\"action_name\": \"action_listen\"}, \"user\": {\"intent\": \"Khoa_Phau_thuat_tao_hinh_tham_my_o_dau?\"}}, {\"prev_action\": {\"action_name\": \"utter_Khoa_Phau_thuat_tao_hinh_tham_my_o_dau?\"}, \"user\": {\"intent\": \"Khoa_Phau_thuat_tao_hinh_tham_my_o_dau?\"}}]",
      "[{\"prev_action\": {\"action_name\": \"action_listen\"}, \"user\": {\"intent\": \"toi_bi_nga_xe\"}}]",
      "[{\"prev_action\": {\"action_name\": \"action_listen\"}, \"user\": {\"intent\": \"Theo_doi_ket_qua_kham_tren_dien_thoai_nhu_the_nao?\"}}, {\"prev_action\": {\"action_name\": \"utter_Theo_doi_ket_qua_kham_tren_dien_thoai_nhu_the_nao?\"}, \"user\": {\"intent\": \"Theo_doi_ket_qua_kham_tren_dien_thoai_nhu_the_nao?\"}}]",
      "[{\"prev_action\": {\"action_name\": \"action_listen\"}, \"user\": {\"intent\": \"Nha_P\"}}, {\"prev_action\": {\"action_name\": \"utter_Nha_P\"}, \"user\": {\"intent\": \"Nha_P\"}}]",
      "[{\"prev_action\": {\"action_name\": \"action_listen\"}, \"user\": {\"intent\": \"Dang_ky_su_dung_the_khach_hang_nhu_the_nao?\"}}, {\"prev_action\": {\"action_name\": \"utter_Dang_ky_su_dung_the_khach_hang_nhu_the_nao?\"}, \"user\": {\"intent\": \"Dang_ky_su_dung_the_khach_hang_nhu_the_nao?\"}}]",
      "[{\"prev_action\": {\"action_name\": \"action_listen\"}, \"user\": {\"intent\": \"Khoa_Noi_nhi_tong_hop_o_dau?\"}}]",
      "[{\"prev_action\": {\"action_name\": \"action_listen\"}, \"user\": {\"intent\": \"toi_bi_tieu_nhieu_vao_ban_dem\"}}, {\"prev_action\": {\"action_name\": \"utter_toi_bi_tieu_nhieu_vao_ban_dem\"}, \"user\": {\"intent\": \"toi_bi_tieu_nhieu_vao_ban_dem\"}}]",
      "[{\"prev_action\": {\"action_name\": \"action_listen\"}, \"user\": {\"intent\": \"Nha_an_benh_vien_o_dau?\"}}]",
      "[{\"prev_action\": {\"action_name\": \"action_listen\"}, \"user\": {\"intent\": \"Khoa_Rang_ham_mat_o_dau\"}}]",
      "[{\"prev_action\": {\"action_name\": \"action_listen\"}, \"user\": {\"intent\": \"toi_di_kham_thai\"}}, {\"prev_action\": {\"action_name\": \"utter_toi_di_kham_thai\"}, \"user\": {\"intent\": \"toi_di_kham_thai\"}}]",
      "[{\"prev_action\": {\"action_name\": \"action_listen\"}, \"user\": {\"intent\": \"Khoa_Phau_thuat_tao_hinh_tham_my_o_dau?\"}}]",
      "[{\"prev_action\": {\"action_name\": \"action_listen\"}, \"user\": {\"intent\": \"Sao_luu_trich_luc_benh_an_o_dau?\"}}, {\"prev_action\": {\"action_name\": \"utter_Sao_luu_trich_luc_benh_an_o_dau?\"}, \"user\": {\"intent\": \"Sao_luu_trich_luc_benh_an_o_dau?\"}}]",
      "[{\"prev_action\": {\"action_name\": \"action_listen\"}, \"user\": {\"intent\": \"Thoi_gian_lam_viec_cua_benh_vien\"}}]",
      "[{\"prev_action\": {\"action_name\": \"action_listen\"}, \"user\": {\"intent\": \"Khoa_noi_tong_hop_o_dau?\"}}, {\"prev_action\": {\"action_name\": \"utter_Khoa_noi_tong_hop_o_dau?\"}, \"user\": {\"intent\": \"Khoa_noi_tong_hop_o_dau?\"}}]",
      "[{\"prev_action\": {\"action_name\": \"action_listen\"}, \"user\": {\"intent\": \"Khoa_Co_xuong_khop_o_dau?\"}}]",
      "[{\"prev_action\": {\"action_name\": \"action_listen\"}, \"user\": {\"intent\": \"toi_bi_ngua\"}}, {\"prev_action\": {\"action_name\": \"utter_toi_bi_ngua\"}, \"user\": {\"intent\": \"toi_bi_ngua\"}}]",
      "[{\"prev_action\": {\"action_name\": \"action_listen\"}, \"user\": {\"intent\": \"Khoa_Kiem_tra_suc_khoe_o_dau?\"}}, {\"prev_action\": {\"action_name\": \"utter_Khoa_Kiem_tra_suc_khoe_o_dau?\"}, \"user\": {\"intent\": \"Khoa_Kiem_tra_suc_khoe_o_dau?\"}}]",
      "[{\"prev_action\": {\"action_name\": \"action_listen\"}, \"user\": {\"intent\": \"Kham_co_xuong_khop_pho_giao_su_o_dau?\"}}, {\"prev_action\": {\"action_name\": \"utter_Kham_co_xuong_khop_pho_giao_su_o_dau?\"}, \"user\": {\"intent\": \"Kham_co_xuong_khop_pho_giao_su_o_dau?\"}}]",
      "[{\"prev_action\": {\"action_name\": \"action_listen\"}, \"user\": {\"intent\": \"Phong_ke_hoach_tong_hop_o_dau?\"}}, {\"prev_action\": {\"action_name\": \"utter_Phong_ke_hoach_tong_hop_o_dau?\"}, \"user\": {\"intent\": \"Phong_ke_hoach_tong_hop_o_dau?\"}}]",
      "[{\"prev_action\": {\"action_name\": \"action_listen\"}, \"user\": {\"intent\": \"Tam_ung_tien\"}}, {\"prev_action\": {\"action_name\": \"utter_Tam_ung_tien\"}, \"user\": {\"intent\": \"Tam_ung_tien\"}}]",
      "[{\"prev_action\": {\"action_name\": \"action_listen\"}, \"user\": {\"intent\": \"toi_bi_dau_tai\"}}]",
      "[{\"prev_action\": {\"action_name\": \"action_listen\"}, \"user\": {\"intent\": \"Khoa_sinh_hoa_o_dau?\"}}]",
      "[{\"prev_action\": {\"action_name\": \"action_listen\"}, \"user\": {\"intent\": \"Khoa_vi_sinh_o_dau?\"}}, {\"prev_action\": {\"action_name\": \"utter_Khoa_vi_sinh_o_dau?\"}, \"user\": {\"intent\": \"Khoa_vi_sinh_o_dau?\"}}]",
      "[{\"prev_action\": {\"action_name\": \"action_listen\"}, \"user\": {\"intent\": \"toi_bi_dau_xuong_khop\"}}, {\"prev_action\": {\"action_name\": \"utter_toi_bi_dau_xuong_khop\"}, \"user\": {\"intent\": \"toi_bi_dau_xuong_khop\"}}]",
      "[{\"prev_action\": {\"action_name\": \"action_listen\"}, \"user\": {\"intent\": \"Tam_ung_tien\"}}]",
      "[{\"prev_action\": {\"action_name\": \"action_listen\"}, \"user\": {\"intent\": \"Khoa_tham_do_chuc_nang_-_noi_soi_o_dau?\"}}]",
      "[{\"prev_action\": {\"action_name\": \"action_listen\"}, \"user\": {\"intent\": \"Nha_ve_sinh__o_dau?\"}}]",
      "[{\"prev_action\": {\"action_name\": \"action_listen\"}, \"user\": {\"intent\": \"toi_bi_di_ngoai\"}}]",
      "[{\"prev_action\": {\"action_name\": \"action_listen\"}, \"user\": {\"intent\": \"Sieu_thi_o_dau?\"}}]",
      "[{\"prev_action\": {\"action_name\": \"action_listen\"}, \"user\": {\"intent\": \"Nha_I\"}}]",
      "[{\"prev_action\": {\"action_name\": \"action_listen\"}, \"user\": {\"intent\": \"toi_bi_ho\"}}]",
      "[{\"prev_action\": {\"action_name\": \"action_listen\"}, \"user\": {\"intent\": \"Khoa_San_o_dau?\"}}, {\"prev_action\": {\"action_name\": \"utter_Khoa_San_o_dau?\"}, \"user\": {\"intent\": \"Khoa_San_o_dau?\"}}]",
      "[{\"prev_action\": {\"action_name\": \"action_listen\"}, \"user\": {\"intent\": \"toi_bi_ngat_mui\"}}, {\"prev_action\": {\"action_name\": \"utter_toi_bi_ngat_mui\"}, \"user\": {\"intent\": \"toi_bi_ngat_mui\"}}]",
      "[{\"prev_action\": {\"action_name\": \"action_listen\"}, \"user\": {\"intent\": \"Tra_so_BHYT_o_dau?\"}}]",
      "[{\"prev_action\": {\"action_name\": \"action_listen\"}, \"user\": {\"intent\": \"Sao_luu_trich_luc_benh_an_o_dau?\"}}]",
      "[{\"prev_action\": {\"action_name\": \"action_listen\"}, \"user\": {\"intent\": \"Em_muon_dang_ki_kham_theo_yeu_cau\"}}, {\"prev_action\": {\"action_name\": \"utter_Em_muon_dang_ki_kham_theo_yeu_cau\"}, \"user\": {\"intent\": \"Em_muon_dang_ki_kham_theo_yeu_cau\"}}]",
      "[{\"prev_action\": {\"action_name\": \"action_listen\"}, \"user\": {\"intent\": \"Khoa_than_tiet_nieu_va_loc_mau_o_dau?\"}}]",
      "[{\"prev_action\": {\"action_name\": \"action_listen\"}, \"user\": {\"intent\": \"Em_muon_dang_ki_kham_bao_hiem_y_te\"}}, {\"prev_action\": {\"action_name\": \"utter_Em_muon_dang_ki_kham_bao_hiem_y_te\"}, \"user\": {\"intent\": \"Em_muon_dang_ki_kham_bao_hiem_y_te\"}}]",
      "predicting default action with intent session_start",
      "[{\"prev_action\": {\"action_name\": \"action_listen\"}, \"user\": {\"intent\": \"Khoa_ung_buou_o_dau?\"}}]",
      "[{\"prev_action\": {\"action_name\": \"action_listen\"}, \"user\": {\"intent\": \"toi_bi_dau_hong\"}}]",
      "[{\"prev_action\": {\"action_name\": \"action_listen\"}, \"user\": {\"intent\": \"toi_bi_dau_bung\"}}, {\"prev_action\": {\"action_name\": \"utter_toi_bi_dau_bung\"}, \"user\": {\"intent\": \"toi_bi_dau_bung\"}}]",
      "[{\"prev_action\": {\"action_name\": \"action_listen\"}, \"user\": {\"intent\": \"Thu_ngan_o_dau?\"}}]",
      "[{\"prev_action\": {\"action_name\": \"action_listen\"}, \"user\": {\"intent\": \"toi_muon_noi_soi_da_day\"}}, {\"prev_action\": {\"action_name\": \"utter_toi_muon_noi_soi_da_day\"}, \"user\": {\"intent\": \"toi_muon_noi_soi_da_day\"}}]",
      "[{\"prev_action\": {\"action_name\": \"action_listen\"}, \"user\": {\"intent\": \"Khoa_ngoai_chan_thuong_o_dau?\"}}, {\"prev_action\": {\"action_name\": \"utter_Khoa_ngoai_chan_thuong_o_dau?\"}, \"user\": {\"intent\": \"Khoa_ngoai_chan_thuong_o_dau?\"}}]",
      "[{\"prev_action\": {\"action_name\": \"action_listen\"}, \"user\": {\"intent\": \"Khoa_Co_xuong_khop_o_dau?\"}}, {\"prev_action\": {\"action_name\": \"utter_Khoa_Co_xuong_khop_o_dau?\"}, \"user\": {\"intent\": \"Khoa_Co_xuong_khop_o_dau?\"}}]",
      "[{\"prev_action\": {\"action_name\": \"action_listen\"}, \"user\": {\"intent\": \"toi_bi_dau_rang\"}}, {\"prev_action\": {\"action_name\": \"utter_toi_bi_dau_rang\"}, \"user\": {\"intent\": \"toi_bi_dau_rang\"}}]",
      "[{\"prev_action\": {\"action_name\": \"action_listen\"}, \"user\": {\"intent\": \"Giay_to_can_thiet_kham_la_gi?\"}}]",
      "[{\"prev_action\": {\"action_name\": \"action_listen\"}, \"user\": {\"intent\": \"Nha_thuoc_benh_vien_o_dau?\"}}]",
      "[{\"prev_action\": {\"action_name\": \"action_listen\"}, \"user\": {\"intent\": \"Em_muon_dang_ki_kham_bao_hiem_y_te\"}}]",
      "[{\"prev_action\": {\"action_name\": \"action_listen\"}, \"user\": {\"intent\": \"hoi_an_chua\"}}, {\"prev_action\": {\"action_name\": \"utter_hoi_an_chua\"}, \"user\": {\"intent\": \"hoi_an_chua\"}}]",
      "[{\"prev_action\": {\"action_name\": \"action_listen\"}, \"user\": {\"intent\": \"Phong_kham_ngoai_tong_hop_o_dau?\"}}]",
      "[{\"prev_action\": {\"action_name\": \"action_listen\"}, \"user\": {\"intent\": \"hoi_ten_robot\"}}, {\"prev_action\": {\"action_name\": \"utter_hoi_ten_robot\"}, \"user\": {\"intent\": \"hoi_ten_robot\"}}]",
      "[{\"prev_action\": {\"action_name\": \"action_listen\"}, \"user\": {\"intent\": \"Thu_tuc_nhap_vien\"}}, {\"prev_action\": {\"action_name\": \"utter_Thu_tuc_nhap_vien\"}, \"user\": {\"intent\": \"Thu_tuc_nhap_vien\"}}]",
      "[{\"prev_action\": {\"action_name\": \"action_listen\"}, \"user\": {\"intent\": \"khen_chatbot\"}}]",
      "[{\"prev_action\": {\"action_name\": \"action_listen\"}, \"user\": {\"intent\": \"Kham_co_xuong_khop_pho_giao_su_o_dau?\"}}]",
      "[{\"prev_action\": {\"action_name\": \"action_listen\"}, \"user\": {\"intent\": \"Khoa_tieu_hoa_o_dau?\"}}, {\"prev_action\": {\"action_name\": \"utter_Khoa_tieu_hoa_o_dau?\"}, \"user\": {\"intent\": \"Khoa_tieu_hoa_o_dau?\"}}]",
      "[{\"prev_action\": {\"action_name\": \"action_listen\"}, \"user\": {\"intent\": \"Nha_luu_tru_benh_vien_o_dau?\"}}]",
      "[{\"prev_action\": {\"action_name\": \"action_listen\"}, \"user\": {\"intent\": \"hoi_tuoi_robot\"}}]",
      "[{\"prev_action\": {\"action_name\": \"action_listen\"}, \"user\": {\"intent\": \"Khoa_ngoai_tong_hop_o_dau?\"}}, {\"prev_action\": {\"action_name\": \"utter_Khoa_ngoai_tong_hop_o_dau?\"}, \"user\": {\"intent\": \"Khoa_ngoai_tong_hop_o_dau?\"}}]",
      "[{\"prev_action\": {\"action_name\": \"action_listen\"}, \"user\": {\"intent\": \"toi_bi_tieu_nhieu_vao_ban_dem\"}}]",
      "[{\"prev_action\": {\"action_name\": \"action_listen\"}, \"user\": {\"intent\": \"nlu_fallback\"}}, {\"prev_action\": {\"action_name\": \"utter_please_rephrase\"}, \"user\": {\"intent\": \"nlu_fallback\"}}]",
      "[{\"prev_action\": {\"action_name\": \"action_listen\"}, \"user\": {\"intent\": \"Khoa_y_hoc_co_truyen_o_dau?\"}}, {\"prev_action\": {\"action_name\": \"utter_Khoa_y_hoc_co_truyen_o_dau?\"}, \"user\": {\"intent\": \"Khoa_y_hoc_co_truyen_o_dau?\"}}]",
      "[{\"prev_action\": {\"action_name\": \"action_listen\"}, \"user\": {\"intent\": \"Nha_ve_sinh__o_dau?\"}}, {\"prev_action\": {\"action_name\": \"utter_Nha_ve_sinh__o_dau?\"}, \"user\": {\"intent\": \"Nha_ve_sinh__o_dau?\"}}]",
      "[{\"prev_action\": {\"action_name\": \"action_listen\"}, \"user\": {\"intent\": \"toi_bi_dau_rang\"}}]",
      "[{\"prev_action\": {\"action_name\": \"action_listen\"}, \"user\": {\"intent\": \"toi_bi_dau_dau\"}}, {\"prev_action\": {\"action_name\": \"utter_toi_bi_dau_dau\"}, \"user\": {\"intent\": \"toi_bi_dau_dau\"}}]",
      "[{\"prev_action\": {\"action_name\": \"action_listen\"}, \"user\": {\"intent\": \"Thu_tuc_nhap_vien\"}}]",
      "[{\"prev_action\": {\"action_name\": \"action_listen\"}, \"user\": {\"intent\": \"Nha_H\"}}, {\"prev_action\": {\"action_name\": \"utter_Nha_H\"}, \"user\": {\"intent\": \"Nha_H\"}}]",
      "[{\"prev_action\": {\"action_name\": \"action_listen\"}, \"user\": {\"intent\": \"cam_on\"}}, {\"prev_action\": {\"action_name\": \"utter_cam_on\"}, \"user\": {\"intent\": \"cam_on\"}}]",
      "[{\"prev_action\": {\"action_name\": \"action_listen\"}, \"user\": {\"intent\": \"tam_biet\"}}, {\"prev_action\": {\"action_name\": \"utter_tam_biet\"}, \"user\": {\"intent\": \"tam_biet\"}}]",
      "[{\"prev_action\": {\"action_name\": \"action_listen\"}, \"user\": {\"intent\": \"Kham_co_xuong_khop_thac_si_o_dau?\"}}]",
      "predicting default action with intent back",
      "[{\"prev_action\": {\"action_name\": \"action_listen\"}, \"user\": {\"intent\": \"Khoa_noi_than_kinh_o_dau?\"}}, {\"prev_action\": {\"action_name\": \"utter_Khoa_noi_than_kinh_o_dau?\"}, \"user\": {\"intent\": \"Khoa_noi_than_kinh_o_dau?\"}}]",
      "[{\"prev_action\": {\"action_name\": \"action_listen\"}, \"user\": {\"intent\": \"Nha_C\"}}, {\"prev_action\": {\"action_name\": \"utter_Nha_C\"}, \"user\": {\"intent\": \"Nha_C\"}}]",
      "[{\"prev_action\": {\"action_name\": \"action_listen\"}, \"user\": {\"intent\": \"Nha_B\"}}]",
      "[{\"prev_action\": {\"action_name\": \"action_listen\"}, \"user\": {\"intent\": \"Quan_ca_phe_o_dau?\"}}]",
      "[{\"prev_action\": {\"action_name\": \"action_listen\"}, \"user\": {\"intent\": \"toi_bi_dau_bung\"}}]",
      "[{\"prev_action\": {\"action_name\": \"action_listen\"}, \"user\": {\"intent\": \"lam_duoc_nhung_gi\"}}, {\"prev_action\": {\"action_name\": \"utter_lam_duoc_nhung_gi\"}, \"user\": {\"intent\": \"lam_duoc_nhung_gi\"}}]",
      "[{\"prev_action\": {\"action_name\": \"action_listen\"}, \"user\": {\"intent\": \"Photo_giay_to_o_dau?\"}}]",
      "[{\"prev_action\": {\"action_name\": \"action_listen\"}, \"user\": {\"intent\": \"Khoa_phuc_hoi_chuc_nang_o_dau?\"}}, {\"prev_action\": {\"action_name\": \"utter_Khoa_phuc_hoi_chuc_nang_o_dau?\"}, \"user\": {\"intent\": \"Khoa_phuc_hoi_chuc_nang_o_dau?\"}}]",
      "[{\"prev_action\": {\"action_name\": \"action_listen\"}, \"user\": {\"intent\": \"hoi_ten_robot\"}}]",
      "[{\"prev_action\": {\"action_name\": \"action_listen\"}, \"user\": {\"intent\": \"Khoa_phau_thuat_than_tiet_nieu_&_nam_hoc_o_dau?\"}}, {\"prev_action\": {\"action_name\": \"utter_Khoa_phau_thuat_than_tiet_nieu_&_nam_hoc_o_dau?\"}, \"user\": {\"intent\": \"Khoa_phau_thuat_than_tiet_nieu_&_nam_hoc_o_dau?\"}}]"
    ]
  }
}